{
  "schema_version": "1.0",
  "generated_at": "2026-06-12T15:54:59.421Z",
  "data_mode": "live",
  "record_count": 71,
  "item_count": 5,
  "source_table": "port_vessels",
  "detail_endpoint": "dashboard/api/ports/031/vessels.json",
  "total_count": 71,
  "returned_count": 5,
  "score_distribution": {
    "0_49": 69,
    "50_69": 2,
    "70_84": 0,
    "85_100": 0,
    "unknown": 0
  },
  "priority_counts": {
    "HOT": 2,
    "WARM": 1,
    "LOW": 68
  },
  "actionability_counts": {
    "VERIFY_CONTACT": 10,
    "CONTACT_NOW": 1,
    "MONITOR": 58,
    "HOLD": 2
  },
  "items": [
    {
      "rank": 1,
      "vessel_name": "MINERAL HOPE",
      "imo": "",
      "mmsi": "",
      "call_sign": "ONKD",
      "operator_display": "상록해운주식회사",
      "current_port": "평택·당진",
      "current_port_korean": "평택·당진",
      "normalized_port": {
        "port_code": "031",
        "port_name": "평택·당진",
        "display_name": "평택·당진",
        "raw_port": "Pyeongtaek-Dangjin",
        "raw_aliases": [
          "Pyeongtaek-Dangjin",
          "평택·당진",
          "PORT HEDLAND",
          "평택·당진항"
        ]
      },
      "priority_label": "HOT",
      "actionability_category": "VERIFY_CONTACT",
      "actionability_label": "연락처 확인 필요",
      "opportunity_score": 69,
      "risk_score": 64,
      "confidence_score": 66,
      "missing_fields": [
        "operator_display",
        "contact_person",
        "imo",
        "mmsi"
      ],
      "known_company": "상록해운주식회사",
      "reason_summary": "운영사/회사, 담당자, IMO, MMSI 확인 후 연락 가능한 후보입니다.",
      "recommended_action": "운영선사 확인",
      "port_code": "031",
      "port_name": "평택·당진",
      "port_display_name": "평택·당진",
      "display_name": "평택·당진"
    },
    {
      "rank": 2,
      "vessel_name": "ERSOZ WEST",
      "imo": "",
      "mmsi": "",
      "call_sign": "V7KU4",
      "operator_display": "팬오션 주식회사",
      "current_port": "평택·당진",
      "current_port_korean": "평택·당진",
      "normalized_port": {
        "port_code": "031",
        "port_name": "평택·당진",
        "display_name": "평택·당진",
        "raw_port": "Pyeongtaek-Dangjin",
        "raw_aliases": [
          "Pyeongtaek-Dangjin",
          "평택·당진",
          "포항",
          "평택·당진항"
        ]
      },
      "priority_label": "HOT",
      "actionability_category": "VERIFY_CONTACT",
      "actionability_label": "연락처 확인 필요",
      "opportunity_score": 65,
      "risk_score": 45,
      "confidence_score": 66,
      "missing_fields": [
        "operator_display",
        "contact_person",
        "imo",
        "mmsi"
      ],
      "known_company": "팬오션 주식회사",
      "reason_summary": "운영사/회사, 담당자, IMO, MMSI 확인 후 연락 가능한 후보입니다.",
      "recommended_action": "운영선사 확인",
      "port_code": "031",
      "port_name": "평택·당진",
      "port_display_name": "평택·당진",
      "display_name": "평택·당진"
    },
    {
      "rank": 3,
      "vessel_name": "에이치엘 오셔닉",
      "imo": "",
      "mmsi": "",
      "call_sign": "V7A4617",
      "operator_display": "에이치라인해운(주)",
      "current_port": "평택·당진",
      "current_port_korean": "평택·당진",
      "normalized_port": {
        "port_code": "031",
        "port_name": "평택·당진",
        "display_name": "평택·당진",
        "raw_port": "Pyeongtaek-Dangjin",
        "raw_aliases": [
          "Pyeongtaek-Dangjin",
          "평택·당진",
          "PORT WALCOTT",
          "평택·당진항"
        ]
      },
      "priority_label": "WARM",
      "actionability_category": "VERIFY_CONTACT",
      "actionability_label": "연락처 확인 필요",
      "opportunity_score": 65,
      "risk_score": 45,
      "confidence_score": 66,
      "missing_fields": [
        "operator_display",
        "contact_person",
        "imo",
        "mmsi"
      ],
      "known_company": "에이치라인해운(주)",
      "reason_summary": "운영사/회사, 담당자, IMO, MMSI 확인 후 연락 가능한 후보입니다.",
      "recommended_action": "운영선사 확인",
      "port_code": "031",
      "port_name": "평택·당진",
      "port_display_name": "평택·당진",
      "display_name": "평택·당진"
    },
    {
      "rank": 4,
      "vessel_name": "CMA CGM MONACO",
      "imo": "",
      "mmsi": "",
      "call_sign": "9HA5941",
      "operator_display": "CMA CGM",
      "current_port": "평택·당진",
      "current_port_korean": "평택·당진",
      "normalized_port": {
        "port_code": "031",
        "port_name": "평택·당진",
        "display_name": "평택·당진",
        "raw_port": "Pyeongtaek-Dangjin",
        "raw_aliases": [
          "Pyeongtaek-Dangjin",
          "평택·당진",
          "광양",
          "평택·당진항"
        ]
      },
      "priority_label": "LOW",
      "actionability_category": "CONTACT_NOW",
      "actionability_label": "즉시 연락",
      "opportunity_score": 48,
      "risk_score": 45,
      "confidence_score": 66,
      "missing_fields": [
        "contact_person",
        "imo",
        "mmsi"
      ],
      "known_company": "CMA CGM",
      "reason_summary": "상업 신호와 현재 작업 가능 신호, 연락 경로가 함께 확인됩니다.",
      "recommended_action": "선박 스케줄 확인",
      "port_code": "031",
      "port_name": "평택·당진",
      "port_display_name": "평택·당진",
      "display_name": "평택·당진"
    },
    {
      "rank": 5,
      "vessel_name": "ELEKTRA",
      "imo": "",
      "mmsi": "",
      "call_sign": "LATK8",
      "operator_display": "유코카캐리어스(주)",
      "current_port": "평택·당진",
      "current_port_korean": "평택·당진",
      "normalized_port": {
        "port_code": "031",
        "port_name": "평택·당진",
        "display_name": "평택·당진",
        "raw_port": "Pyeongtaek-Dangjin",
        "raw_aliases": [
          "Pyeongtaek-Dangjin",
          "평택·당진",
          "목포",
          "평택·당진항"
        ]
      },
      "priority_label": "LOW",
      "actionability_category": "VERIFY_CONTACT",
      "actionability_label": "연락처 확인 필요",
      "opportunity_score": 44,
      "risk_score": 45,
      "confidence_score": 66,
      "missing_fields": [
        "operator_display",
        "contact_person",
        "imo",
        "mmsi"
      ],
      "known_company": "유코카캐리어스(주)",
      "reason_summary": "운영사/회사, 담당자, IMO, MMSI 확인 후 연락 가능한 후보입니다.",
      "recommended_action": "운영선사 확인",
      "port_code": "031",
      "port_name": "평택·당진",
      "port_display_name": "평택·당진",
      "display_name": "평택·당진"
    }
  ],
  "warning_summary": [
    {
      "severity": "INFO",
      "feature": "보령항 선박",
      "message": "상세 71건 중 상위 5건만 요약 파일에 포함",
      "recommended_fix": "dashboard/api/ports/031/vessels.json lazy load 사용"
    }
  ]
}
