{
  "schema_version": "1.0",
  "generated_by": "local",
  "is_github_actions": false,
  "validation_mode": "local",
  "serving_mode": "static_json",
  "GITHUB_RUN_ID": null,
  "GITHUB_WORKFLOW": null,
  "run_id": "run_20260613033359476_4972d654",
  "active_run_id": "run_20260613033359476_4972d654",
  "latest_successful_run_id": null,
  "latest_successful_summary_run_id": null,
  "source_run_id": "run_20260613033359476_4972d654",
  "generated_at": "2026-06-13T03:37:05.562Z",
  "status": "available",
  "record_count": 5,
  "item_count": 5,
  "source_key": "source_csv",
  "cache_status": "available",
  "last_success_at": "2026-06-13T01:28:05.305Z",
  "index_counts": {
    "by_imo": 0,
    "by_mmsi": 0,
    "by_call_sign": 1015,
    "by_normalized_vessel_name_call_sign": 1015,
    "by_normalized_vessel_name_gt_vessel_type": 1015
  },
  "indexes": {
    "by_imo": [],
    "by_mmsi": [],
    "by_call_sign": [
      "100933",
      "102740",
      "106783",
      "111002",
      "111844",
      "112815",
      "120004",
      "120011",
      "120021",
      "120050",
      "120059",
      "121835",
      "122820",
      "130010",
      "130024",
      "130029",
      "130037",
      "130047",
      "130063",
      "130064",
      "130088",
      "130095",
      "131062",
      "132825",
      "133507",
      "134806",
      "140035",
      "140052",
      "141033",
      "141076",
      "146804",
      "150012",
      "150035",
      "151058",
      "151802",
      "151819",
      "160019",
      "160028",
      "160031",
      "160040",
      "160049",
      "160063",
      "161001",
      "161008",
      "161047",
      "161063",
      "161822",
      "162805",
      "166807",
      "170002",
      "170004",
      "170009",
      "170014",
      "170024",
      "170030",
      "170035",
      "170036",
      "170037",
      "171071",
      "171825",
      "172811",
      "176801",
      "180003",
      "180005",
      "180006",
      "180010",
      "180020",
      "181056",
      "181814",
      "181823",
      "184803",
      "190013",
      "190026",
      "192801",
      "192827",
      "200009",
      "200013",
      "200031",
      "200033",
      "200035",
      "202809",
      "202810",
      "202813",
      "202823",
      "204007",
      "206808",
      "210003",
      "210016",
      "210036",
      "210041",
      "210043",
      "211024",
      "211802",
      "212803",
      "212838",
      "220009",
      "220023",
      "221827",
      "222801",
      "224805",
      "224806",
      "224810",
      "224814",
      "224816",
      "230007",
      "230010",
      "230014",
      "230023",
      "230025",
      "230026",
      "230034",
      "230047",
      "231023",
      "232813",
      "240001",
      "240017",
      "240018",
      "240019",
      "240023",
      "240026",
      "240029",
      "240047",
      "241811",
      "242817",
      "242826",
      "244401",
      "244807",
      "250025",
      "260002",
      "782385",
      "882285",
      "885116",
      "886630",
      "920411",
      "920665",
      "932171",
      "940514",
      "942504",
      "950023",
      "950536",
      "954325",
      "954516",
      "960625",
      "962050",
      "965128",
      "968921",
      "969070",
      "969115",
      "970431",
      "971467",
      "975981",
      "999018",
      "ONKD",
      "V7B3347",
      "HOYL",
      "BOCT5",
      "V7JH8",
      "8PSO2",
      "5LML3",
      "V7KU4",
      "V7A4617",
      "DYTK",
      "3E6928",
      "V7A3508",
      "5LYO4",
      "V7A2046",
      "BUQZ",
      "KLBO",
      "9VEQ7",
      "7KSY",
      "V7B2724",
      "3EUO7",
      "V7A3317",
      "PCPA",
      "D5TM2",
      "3FRH6",
      "3E3945",
      "3FES7",
      "5LIM3",
      "A8XJ6",
      "D5XU7",
      "V7B2857",
      "V7A4485",
      "5LTT5",
      "DSQP3",
      "D5MF8",
      "5LWW7",
      "V7HA2",
      "9M3117",
      "9VBO3",
      "V7A6226",
      "V7B2782",
      "VRIK8",
      "A8PL6",
      "DSMB",
      "SVCM6",
      "D7OM",
      "9V6841",
      "D5ZT5",
      "V7DJ7",
      "VROQ3",
      "5LCP6",
      "V7NX2",
      "D7HB",
      "5LSB8",
      "3E8356",
      "D8ML",
      "3E7083",
      "3E8048",
      "C6AX3",
      "9HA5941",
      "5LLW3",
      "D5NB7",
      "5LHE8",
      "5LUT3",
      "5LLW4",
      "V7QJ9",
      "SVEA8",
      "SVDR5",
      "3FTV3",
      "9HTD9",
      "H3MM",
      "SVEB8",
      "V7A2485",
      "V7TV3",
      "LATK8",
      "D7IZ",
      "MOLL9",
      "C6CN3",
      "SVAX5",
      "V7HQ3",
      "3EWB4",
      "5BKW6",
      "D5GW5",
      "D5SM2",
      "D7KR",
      "V7GV9",
      "C6KM7",
      "H8WY",
      "D5YL3",
      "9HA4902",
      "9HA5600",
      "C6BE4",
      "H9DA",
      "5LTE9",
      "BURT",
      "D5XD8",
      "3FTP3",
      "2ICI4",
      "3E5241",
      "5LQW3",
      "3FRS4",
      "SVBM2",
      "HZLA",
      "V7A3394",
      "VRPG6",
      "5LQI5",
      "D7NC",
      "OYRO2",
      "3E6987",
      "7KHL",
      "D7EW",
      "5LFF5",
      "9V7760",
      "D5HE9",
      "9V9990",
      "9V6730",
      "V7GO3",
      "5LYI6",
      "D5UJ6",
      "CQEU6",
      "3E8944",
      "J5AQ1",
      "V7B2802",
      "ZCHI3",
      "HOA2246",
      "D5QH6",
      "5LYE9",
      "9VMW8",
      "9HA6318",
      "WLPI",
      "D8EY",
      "7KBS",
      "9HA5926",
      "BLHL",
      "C6EK6",
      "7JWL",
      "VRNR5",
      "9V9625",
      "9V8787",
      "9V3454",
      "5LOS7",
      "C4PW2",
      "5LMA3",
      "5LBD9",
      "V7A3322",
      "D5MX5",
      "9VVD3",
      "5LXW5",
      "LAQQ7",
      "C6VH5",
      "T8A5034",
      "9HA3008",
      "9HA4858",
      "LAYM8",
      "C6FE7",
      "3FRA8",
      "DYEU",
      "D7OF",
      "9HA5007",
      "3ELB7",
      "OZCV2",
      "9VDC8",
      "VRQC9",
      "VTOD",
      "9V5244",
      "D7AH",
      "VRMX7",
      "DHDT2",
      "D7UC",
      "3EWV5",
      "D7YF",
      "DSQJ6",
      "H3AP",
      "WAIU",
      "V7FM4",
      "9HA3539",
      "C6VF2",
      "3FWR3",
      "C6RI2",
      "5LJZ9",
      "V7A7494",
      "9HA6117",
      "9VDK5",
      "UAWE6",
      "YJSE3",
      "3FCW",
      "2ELO7",
      "V7B2847",
      "5LDN8",
      "BOCL8",
      "V7A7228",
      "C6DO5",
      "V7A4868",
      "HPQI",
      "3E6113",
      "3E3444",
      "3ECE2",
      "V7QM5",
      "V7LN4",
      "BPKL",
      "3FAR9",
      "9MFE7",
      "D5CA9",
      "SVCB7",
      "D8BJ",
      "9HA4560",
      "D7GT",
      "VRNT9",
      "DSQF4",
      "9V3757",
      "D5XC6",
      "9V7977",
      "2ICT5",
      "3FRY7",
      "3FVS",
      "9V2729",
      "5LQF5",
      "J5AR7",
      "7JCK",
      "300PRETTY",
      "D7CQ",
      "9LU2825",
      "D5EM2",
      "DSRD9",
      "DSRA2",
      "CQIG8",
      "V7GE2",
      "WDM2203",
      "BPAQ",
      "V3JW2",
      "D7SH",
      "5LTZ7",
      "V7QL3",
      "9VMT2",
      "HOA8046",
      "5LLO9",
      "ELSN9",
      "3E2119",
      "VRGG4",
      "V7A5457",
      "9V2407",
      "D7GQ",
      "DSQI2",
      "V7KG7",
      "5LLL8",
      "KTTB",
      "3EA4144",
      "V7A6056",
      "KTTE",
      "D7DL",
      "D8BD",
      "VRQJ4",
      "DSRP4",
      "D8AG",
      "9V6325",
      "9V2552",
      "9V8649",
      "DSMD",
      "V7A4482",
      "9V8780",
      "S6UJ9",
      "3E9011",
      "BURS",
      "V7AK6",
      "V7VF8",
      "C6XC6",
      "H9MW",
      "D7UV",
      "DSQN2",
      "D7EF",
      "A8SJ3",
      "5LRV2",
      "5LNE2",
      "D7FP",
      "VRSS8",
      "5LLJ6",
      "5LEG6",
      "BPCR7",
      "CQ2132",
      "9V3808",
      "D7DG",
      "D7FS",
      "D7FG",
      "3FEK7",
      "D7AT",
      "DSFN9",
      "D5TH5",
      "D7BW",
      "V7XQ8",
      "CQZG",
      "D7SJ",
      "9V9003",
      "D5JY4",
      "D7AA",
      "BPLL9",
      "DSRI7",
      "WPCW",
      "PCUC",
      "D7ZP",
      "D7LL",
      "HZFD",
      "D7LG",
      "DSRK4",
      "300TNLETO",
      "D8SV",
      "3FAL8",
      "5LRZ9",
      "D7SK",
      "LADO6",
      "9V6634",
      "IBZE",
      "DYTI",
      "LAXA8",
      "3E6122",
      "A8YZ6",
      "V7JS3",
      "A8ZS9",
      "3EFZ3",
      "9HA4133",
      "5VIS4",
      "VRTS5",
      "088443",
      "D7RO",
      "3E5300",
      "3E3743",
      "V7A6165",
      "3E7009",
      "DSIU5",
      "070606",
      "A8UZ4",
      "9V5491",
      "BOXF3",
      "H3XM",
      "V7UF2",
      "4OCS",
      "CQ2873",
      "C6LB9",
      "SVCH5",
      "DSPQ4",
      "V7PU7",
      "3EZG6",
      "5LHI7",
      "3EVE2",
      "A8CM9",
      "5LRT6",
      "3WSY9",
      "3E7078",
      "V7A6181",
      "3EWK9",
      "3EHP8",
      "3EYL6",
      "3E4678",
      "V7HP8",
      "VRRP2",
      "V7B2983",
      "V7FU4",
      "HO9294",
      "3FQP5",
      "C6GU2",
      "9HA5466",
      "5LFC4",
      "5LFB7",
      "9HA6254",
      "VRXM3",
      "D7EE",
      "9HJF9",
      "DSQJ9",
      "V7B3139",
      "DSFM6",
      "3E8432",
      "VRDH9",
      "5BXJ6",
      "HOA3374",
      "DSMS2",
      "3ECG6",
      "D7PG",
      "DSRG6",
      "DSQU4",
      "D7IY",
      "D5HE5",
      "HO5909",
      "D7VA",
      "CQ2193",
      "3FHW3",
      "3E8772",
      "D8BV",
      "VRIC3",
      "DSQP2",
      "3E6905",
      "V7DC3",
      "D7HS",
      "3E8992",
      "D5ZO5",
      "D7OY",
      "D7TS",
      "5LMN7",
      "D7XP",
      "3E7842",
      "D7UA",
      "D7BH",
      "D8FA",
      "XVHR7",
      "V7ER5",
      "VRTX9",
      "9V8010",
      "3E3843",
      "3E8847",
      "3FHO8",
      "3E4723",
      "3E3614",
      "9V8001",
      "VRCX3",
      "V7A5540",
      "3FHB3",
      "D8CM",
      "BQTK",
      "D7ID",
      "D7ND",
      "V7ZR2",
      "D7HW",
      "5LLR8",
      "5LJL5",
      "H8BZ",
      "3E5968",
      "V7A5912",
      "VRQQ3",
      "VRWF4",
      "LAGX8",
      "3E3921",
      "D7GC",
      "D8BF",
      "D5FF4",
      "3EZZ6",
      "D7CC",
      "3E3693",
      "D8DJ",
      "H9ZG",
      "D7FU",
      "D8RV",
      "DSNA3",
      "A8TR7",
      "9V7910",
      "D5CE3",
      "3ECW9",
      "3E3441",
      "3FPM7",
      "3E5038",
      "5IM597",
      "5BFP5",
      "J8TH8",
      "D7DP",
      "9VFL3",
      "HOLT",
      "DSOA9",
      "D7XJ",
      "3EUE6",
      "BPES2",
      "9LS2285",
      "5IM886",
      "D7GH",
      "3E7786",
      "3E8435",
      "D5QC7",
      "D7ER",
      "3E5221",
      "DSAJ3",
      "3FBA4",
      "9V9638",
      "KDAB",
      "DSOU4",
      "3E3870",
      "V7A6129",
      "V7IQ5",
      "9VFW9",
      "3E4746",
      "3FCY9",
      "3FZM6",
      "VROO8",
      "J5BG3",
      "V7ER6",
      "BPIT5",
      "D7PP",
      "9LS2184",
      "030968",
      "WDM3306",
      "021568",
      "A8MR8",
      "3E8496",
      "V3IP",
      "3FDF8",
      "V2FY7",
      "VRIH8",
      "LAFY8",
      "D5YE8",
      "S9Z1",
      "3E5367",
      "D8TG",
      "3EZP2",
      "9V7919",
      "H3OI",
      "BPOB2",
      "3E3956",
      "BPNA5",
      "VREG9",
      "3E8762",
      "BPJR2",
      "V7A4978",
      "6YXV7",
      "V7DU4",
      "3FMT9",
      "V7A4450",
      "5LOD9",
      "VRUY7",
      "D7SP",
      "3ESH2",
      "D7DI",
      "D7CV",
      "BOSP6",
      "D7KS",
      "V3QM3",
      "BPKY8",
      "9V8011",
      "3EEF9",
      "D7MT",
      "BQQR",
      "DSEK8",
      "3E8387",
      "060821",
      "D7XD",
      "UBFY7",
      "VRYA6",
      "3FLI8",
      "5LTW2",
      "9V2137",
      "V3BJ3",
      "3EDY8",
      "5LJR5",
      "DSJA6",
      "V7QU5",
      "3E7177",
      "PCIG",
      "V7A2621",
      "D7TR",
      "D7UZ",
      "300STFR",
      "9V7999",
      "DSRB4",
      "9V8713",
      "CQ2099",
      "CQOP",
      "BOBO6",
      "5LKO8",
      "VRGM4",
      "5LOE2",
      "V2GK7",
      "DSQQ4",
      "3E8459",
      "D7WH",
      "H3OA",
      "D7CI",
      "BPEF2",
      "DSQT6",
      "3E2180",
      "092615",
      "PBUC",
      "VRQU8",
      "3FIP7",
      "3E4972",
      "3E8325",
      "5LFT9",
      "3E2538",
      "TYG18",
      "D7JE",
      "DSQT9",
      "VRWA5",
      "3E3872",
      "D8TI",
      "3EBG4",
      "3E8450",
      "V2HJ4",
      "BSDU",
      "3E2567",
      "3E2619",
      "008346",
      "V3VQ6",
      "3E4671",
      "D5KW6",
      "V7UY6",
      "DYHY",
      "3E8488",
      "3WPG",
      "DSQA4",
      "BQBK7",
      "D7PC",
      "3E7469",
      "3E8662",
      "D7CO",
      "D7BC",
      "V7A2844",
      "3FRF8",
      "3E8451",
      "V3UW2",
      "DSFA",
      "V2GN7",
      "9V8013",
      "VRTL4",
      "5IM811",
      "D7BR",
      "VRNZ6",
      "V3PP",
      "HLLN",
      "UAJO",
      "UEAJ",
      "UBBE",
      "D7YA",
      "D7UO",
      "3FNI2",
      "C6TQ2",
      "S9A8",
      "H3OX",
      "3E8980",
      "VRVY3",
      "9V3759",
      "D9AC",
      "3FUN2",
      "D7EB",
      "3E9007",
      "D7VU",
      "D7BU",
      "XVDB7",
      "LALK8",
      "D5YS3",
      "C6TN2",
      "D7CH",
      "9V9142",
      "V7LN2",
      "PCMV",
      "UBEI3",
      "E6CN3",
      "3FBF6",
      "7JQW",
      "D8DX",
      "3FTH3",
      "H3VB",
      "V3ND9",
      "9V7559",
      "9V8440",
      "3E7418",
      "DSEZ7",
      "D7BN",
      "BOOA",
      "3FXP5",
      "3E8838",
      "DSRP5",
      "3EOM3",
      "D7LI",
      "D7UQ",
      "3E2788",
      "BPDN8",
      "D7HY",
      "D7ZY",
      "BPPF3",
      "3FMN5",
      "HONQ",
      "DSNB9",
      "DSNG8",
      "3FNA8",
      "LAMJ7",
      "D7TX",
      "3E8686",
      "3FJT4",
      "BOAU9",
      "3ETQ2",
      "9V6745",
      "3E8769",
      "S9Z16",
      "V3PV8",
      "D7WR",
      "DSAC3",
      "6YWZ8",
      "D7FJ",
      "9LU2920",
      "DSQJ2",
      "3ENO5",
      "D7DM",
      "D7QL",
      "HO6237",
      "D5MB8",
      "3E7460",
      "3E3839",
      "DSRB5",
      "V3BX2",
      "BOQA9",
      "V3ZX",
      "D8DC",
      "DSHP6",
      "D7RJ",
      "3E6645",
      "CSB8001",
      "V3GC2",
      "J5AW2",
      "VRWI8",
      "DSQW7",
      "D7EN",
      "V3NA",
      "3E3763",
      "9LU2481",
      "3E8314",
      "062928",
      "V7A7350",
      "J5AU1",
      "V3AE",
      "V3MW4",
      "3ESJ9",
      "3E8925",
      "9V7049",
      "V3HU2",
      "050626",
      "D7SS",
      "V3MX2",
      "HOA7205",
      "V3LM2",
      "V3CY3",
      "HOA5934",
      "S9A3142",
      "5LLR9",
      "D7NE",
      "CQIX5",
      "DSQA3",
      "D6A4061",
      "H3RB",
      "LAYP4",
      "V7A2776",
      "V7A3541",
      "3EDK5",
      "3E6752",
      "3E8470",
      "BTDW",
      "3FTI8",
      "9V6167",
      "DSFT8",
      "D8FB",
      "9HB2079",
      "C6TJ9",
      "3E7853",
      "UBGF6",
      "3EFG6",
      "080122",
      "DSPF9",
      "9V5189",
      "3E7270",
      "092219",
      "9V7740",
      "9LU2611",
      "9LU2546",
      "D8HX",
      "D8BU",
      "046546",
      "DSOD5",
      "3E8749",
      "D7TO",
      "D7AD",
      "V7JZ7",
      "DSPL3",
      "6KSG",
      "D7RH",
      "UBIZ7",
      "5LQC9",
      "DSPH2",
      "062974",
      "D7TM",
      "H9HG",
      "3EZT8",
      "3ESK6",
      "DSPF4",
      "050481",
      "DSDU4",
      "JG5720",
      "D7TQ",
      "3E6941",
      "HOA2618",
      "3FYN5",
      "HOA4554",
      "DSQL7",
      "D7VW",
      "3E8393",
      "DSAU",
      "V3VD3",
      "DSQY5",
      "DSFJ2",
      "D8CS",
      "DSPD6",
      "DSGR",
      "080444",
      "079991",
      "DSFB",
      "3FMM5",
      "DSFJ4",
      "V7A3474",
      "6LZM",
      "D7MJ",
      "T8A3940",
      "J5BE1",
      "9LS2189",
      "3EJQ3",
      "DSOA2",
      "DSPF5",
      "040491",
      "DSJA4",
      "D7DZ",
      "D7JO",
      "039076",
      "UBIZ3",
      "DSGZ",
      "UBIZ4",
      "UCPG",
      "UHJK",
      "6YWG7",
      "UGBT",
      "D7RF",
      "071203",
      "BZV5N",
      "UBCH",
      "T3FQ",
      "UBRW5",
      "3E3399",
      "DSNH2",
      "3EYQ5",
      "BPPV2",
      "3FTX3",
      "073141",
      "070890",
      "DSNR6",
      "DSOY4",
      "J5BE8",
      "T8A4488",
      "6LZQ",
      "UDRM",
      "UBJT8",
      "UBRX",
      "070592",
      "BOLV4",
      "HPUO",
      "3EUS5",
      "DSFS8",
      "BZW7N",
      "BZW2O",
      "BZW1O",
      "032583",
      "021285",
      "DSFV3",
      "7KNG",
      "DSPZ6",
      "086790",
      "085633",
      "DSQK5",
      "D8WQ",
      "HOKX",
      "9LS2091",
      "031342",
      "D7YK",
      "042092",
      "060181",
      "080193"
    ],
    "by_normalized_vessel_name_call_sign": [
      "MINERAL HOPE|ONKD",
      "MARCEL|V7B3347",
      "BERGE DOI INTHANON|HOYL",
      "BEI HAI FENG HUANG|BOCT5",
      "CF DIAMOND|V7JH8",
      "VITUS BERING|8PSO2",
      "PAN PEGASUS|5LML3",
      "ERSOZ WEST|V7KU4",
      "에이치엘 오셔닉|V7A4617",
      "ORION TRADER|DYTK",
      "FIONAN|3E6928",
      "스키야토스|V7A3508",
      "HL PORT HEDLAND|5LYO4",
      "KOBAYASHI MARU|V7A2046",
      "CHANG HANG HU PO|BUQZ",
      "WASHINGTON|KLBO",
      "CONDOR|9VEQ7",
      "SAKURA CRESCENT|7KSY",
      "GENCO STARS AND STRIPES|V7B2724",
      "ONE TREASURE|3EUO7",
      "DHT REDWOOD|V7A3317",
      "한유울산|210041",
      "CORAL ALICIA|PCPA",
      "MSC FAITH|D5TM2",
      "MSC IVANA|3FRH6",
      "세양글로리|140052",
      "PRISM COURAGE|3E3945",
      "에이치엘 그린|3FES7",
      "OMAHA|5LIM3",
      "FPMC C MELODY|A8XJ6",
      "NAVE ALLEGRO|D5XU7",
      "FRONT SPEY|V7B2857",
      "ARDMORE PURSUIT|V7A4485",
      "23부광호|230014",
      "HMM TURQUOISE|5LTT5",
      "스카이 글로리|DSQP3",
      "스카이케미|160063",
      "MSC MIRJAM|D5MF8",
      "MSC ALESSIA|5LWW7",
      "OLYMPIC TRUST|V7HA2",
      "EAGLE VELLORE|9M3117",
      "FMG AMANDA|9VBO3",
      "PUTERI SEJINJANG|V7A6226",
      "WOOYANG ARES|V7B2782",
      "SEAMERIDIAN|VRIK8",
      "LIA|A8PL6",
      "디엘 앰버|211024",
      "우혁|DSMB",
      "SEA PEARL|SVCM6",
      "씨 챌린저|D7OM",
      "KN BLOSSOM|9V6841",
      "PACIFIC MOONSTONE|D5ZT5",
      "STI CONNAUGHT|V7DJ7",
      "NEW SOLUTION|VROQ3",
      "ANDES|5LCP6",
      "NAVIOS INDIGO|V7NX2",
      "에이치엠엠 방콕|D7HB",
      "HMM TOPAZ|5LSB8",
      "ROMANCE|3E8356",
      "MORNING LADY|D8ML",
      "FLORA MARIS|3E7083",
      "BELFUTURE|3E8048",
      "ASIA VISION|C6AX3",
      "CMA CGM MONACO|9HA5941",
      "MSC VALENTINA|5LLW3",
      "MSC TINA|D5NB7",
      "MSC TESSA|5LHE8",
      "MSC ANNAMARIA|5LUT3",
      "MSC METTE|5LLW4",
      "HYUNDAI VOYAGER|V7QJ9",
      "SEA ORCA|SVEA8",
      "ALEXANDRA|SVDR5",
      "TEAL BULKER|3FTV3",
      "MILAGRO|9HTD9",
      "MORNING SALUTE|H3MM",
      "MARAN GAS ANTIPAROS|SVEB8",
      "MAY|V7A2485",
      "MAR CAMINO|V7TV3",
      "ELEKTRA|LATK8",
      "글로벌 파이오니어|D7IZ",
      "UBUNTU SINCERITY|MOLL9",
      "DANAE R|C6CN3",
      "DIAMANTINA|SVAX5",
      "F SUN|V7HQ3",
      "PAN IRIS|3EWB4",
      "SEABEAUTY|5BKW6",
      "LYDIA OLDENDORFF|D5GW5",
      "LUCY OLDENDORFF|D5SM2",
      "PAN COSMOS|D7KR",
      "HAFNIA ALMANDINE|V7GV9",
      "한남|206808",
      "ASIA SPRING|C6KM7",
      "GLOBAL HOSPITALITY|H8WY",
      "MISSION REVIVAL|D5YL3",
      "MSC BELLISSIMA|9HA4902",
      "CMA CGM SYMI|9HA5600",
      "아프리칸 스타링|C6BE4",
      "PATHFINDER|H9DA",
      "HIGH MARINER|5LTE9",
      "CHANG HANG FEI CUI|BURT",
      "SOLAR KAREN|D5XD8",
      "FLAG ZANNIS|3FTP3",
      "KMARIN RESOLUTION|2ICI4",
      "NAVE POLARIS|3E5241",
      "SAPPHIRE ETERNITY|5LQW3",
      "FEDERAL ILLINOIS|3FRS4",
      "피갈리아 나비게이터|SVBM2",
      "SARA|HZLA",
      "YASA LEOPARD|V7A3394",
      "SEAODYSSEY|VRPG6",
      "뉴동신호|120004",
      "타히티|260002",
      "HMM EMERALD|5LQI5",
      "흥아 하이퐁|D7NC",
      "CLIFFORD MAERSK|OYRO2",
      "AC VICTORY|3E6987",
      "GT ATHENA|7KHL",
      "HMM BLESSING|D7EW",
      "YM TUTORIAL|5LFF5",
      "SEASPAN PRIDE|9V7760",
      "COCHRANE|D5HE9",
      "ZIM WILMINGTON|9V9990",
      "MSC ANTIGUA|9V6730",
      "SAN FERNANDO|V7GO3",
      "MANZANILLO EXPRESS|5LYI6",
      "GSL NINGBO|D5UJ6",
      "MSC LILY|CQEU6",
      "에이치엠엠 리프|3E8944",
      "신정3호|170002",
      "비케이 25|240026",
      "WAN MING HE XIE|J5AQ1",
      "SILK JAKARTA|V7B2802",
      "DIAMOND PRINCESS|ZCHI3",
      "씨호라이즌호|160040",
      "ADORA MAGIC CITY|HOA2246",
      "MSC EMMA|D5QH6",
      "STAR STAMFORD|5LYE9",
      "스카이마스|230010",
      "SEASPAN BRAVO|9VMW8",
      "CMA CGM PLATINUM|9HA6318",
      "LIBERTY PASSION|WLPI",
      "글로비스 세이프티|D8EY",
      "ONE WREN|7KBS",
      "CMA CGM BUZIOS|9HA5926",
      "YM UNANIMITY|BLHL",
      "CMA CGM HYDRA|C6EK6",
      "ONE COMPETENCE|7JWL",
      "OOCL UTAH|VRNR5",
      "ONE SPARKLE|9V9625",
      "SEASPAN ADONIS|9V8787",
      "ONE COSMOS|9V3454",
      "ZENITH LUMOS|5LOS7",
      "LE HAVRE|C4PW2",
      "VIENNA EXPRESS|5LMA3",
      "NEW FIRST|5LBD9",
      "ETHANE CORAL|V7A3322",
      "STOLT LOTUS|D5MX5",
      "BW TOKYO|9VVD3",
      "GLOVIS TREASURE|5LXW5",
      "STAR LYSEFJORD|LAQQ7",
      "라피스 어로우|C6VH5",
      "DMC JUPITER|T8A5034",
      "NBA MONET|9HA3008",
      "TOSCANA|9HA4858",
      "NOCC PACIFIC|LAYM8",
      "해창썬|240023",
      "ADORA MEDITERRANEA|C6FE7",
      "GRAND DAHLIA|3FRA8",
      "EPSON TRADER|DYEU",
      "GLOVIS COMET|D7OF",
      "CMA CGM CASSIOPEIA|9HA5007",
      "GNS HARVEST|3ELB7",
      "TORM EVA|OZCV2",
      "NAVIG8 MESSI|9VDC8",
      "CHALLENGE PRELUDE|VRQC9",
      "LILAC VICTORIA|VTOD",
      "부광5호|210016",
      "MAERSK SARNIA|9V5244",
      "에스제이 호프|D7AH",
      "OOCL SINGAPORE|VRMX7",
      "PARANA|DHDT2",
      "케이엠티씨 선전|D7UC",
      "우현|161063",
      "POAVOSA ACE|3EWV5",
      "JN JUPITER|D7YF",
      "성호 에이스호|DSQJ6",
      "PALMELA|H3AP",
      "페트리어트|WAIU",
      "MORNING PRIDE|V7FM4",
      "테르모필레|9HA3539",
      "타이판|C6VF2",
      "ORCA PEARL|3FWR3",
      "CRYSTAL RAY|C6RI2",
      "LAKE TAZAWA|5LJZ9",
      "PAGANELLA|V7A7494",
      "CMA CGM MONZA|9HA6117",
      "AURORA GUARDIAN|9VDK5",
      "AKSEL|UAWE6",
      "ORIENTAL PARALLEL|YJSE3",
      "LOCH LONG|3FCW",
      "NOBLE ACE|2ELO7",
      "ABRACADABRA|V7B2847",
      "HSL VEGAS|5LDN8",
      "WEI LUN JU LONG|BOCL8",
      "AGIA SOFIA I|V7A7228",
      "STAR ATLAS|C6DO5",
      "HYUNDAI OCEANPIA|V7A4868",
      "PROGRESS ACE|HPQI",
      "TURQUOISE ACE|3E6113",
      "PAN MAJESTY|3E3444",
      "SHANGHAI HIGHWAY|3ECE2",
      "WOOYANG BANDERS|V7QM5",
      "GALAXY GLOBE|V7LN4",
      "XIN CANG ZHOU|BPKL",
      "펜타|3FAR9",
      "SERI AYU|9MFE7",
      "VIKTOR TSOI|D5CA9",
      "MARAN GAS LINDOS|SVCB7",
      "카라호|D8BJ",
      "OCEAN FUTURE|9HA4560",
      "호프 만|D7GT",
      "OSLO VENTURE|VRNT9",
      "케이티에스 화이트|DSQF4",
      "HAFNIA TAGUS|9V3757",
      "부양에이스|120059",
      "YM TARGET|D5XC6",
      "EVER FORWARD|9V7977",
      "에코 가스|240018",
      "티앤 레아|171071",
      "BW CARINA|2ICT5",
      "NBA MILLET|3FRY7",
      "G DOLCE|3FVS",
      "SANSOVINO|9V2729",
      "VALLEE BLANCHE|5LQF5",
      "HENG XING FA ZHAN|J5AR7",
      "ENERGY NAVIGATOR|7JCK",
      "프리티 프로스페리티|300PRETTY",
      "광산|112815",
      "유한1호|162805",
      "우진|D7CQ",
      "제7현진호|232813",
      "HU PO|9LU2825",
      "제8우진호|212838",
      "ENSENADA|D5EM2",
      "KMTC ULSAN|DSRD9",
      "SINOKOR NIIGATA|DSRA2",
      "MSC JERSEY|CQIG8",
      "INTERLINK SOLIDITY|V7GE2",
      "MISSOURI EXPRESS|WDM2203",
      "XIN TIAN JIN|BPAQ",
      "XING YU 68|V3JW2",
      "케이엠티씨 제벨 알리|D7SH",
      "MSC UNITE VI|5LTZ7",
      "HYUNDAI SUPREME|V7QL3",
      "SEASPAN RIO DE JANEIRO|9VMT2",
      "SEASTAR HAWK|HOA8046",
      "MELBORNE BRIDGE|5LLO9",
      "STOLT CAPABILITY|ELSN9",
      "CS HANA|3E2119",
      "STOLT VOYAGER|VRGG4",
      "HANSA SEALANCER|V7A5457",
      "EAGLE ASIA 11|9V2407",
      "슈퍼 이스턴|D7GQ",
      "로터스 삼부|DSQI2",
      "SEAWAYS WARWICK|V7KG7",
      "VOYAGER|5LLL8",
      "TORM THUNDER|KTTB",
      "ORIENTAL SUNSTONE|3EA4144",
      "GREAT WHITE|V7A6056",
      "TORM TIMOTHY|KTTE",
      "우황|D7DL",
      "미시칸|D8BD",
      "OAK EXPRESS|VRQJ4",
      "한유 빅토리아|DSRP4",
      "아시안 그레이스|D8AG",
      "PETREL PACIFIC|9V6325",
      "HAFNIA PANTHER|9V2552",
      "SUN MERCURY|9V8649",
      "우림 5|DSMD",
      "CL YINGDU|V7A4482",
      "STOLT AJISAI|9V8780",
      "CLYNELISH|S6UJ9",
      "JIN HANG 89|3E9011",
      "CHANG HANG ZUAN SHI|BURS",
      "THE PROSPECTOR|V7AK6",
      "STI ESLES II|V7VF8",
      "MITSUI OCEAN FUJI|C6XC6",
      "MSC ALYSSA|H9MW",
      "동진 피데스|D7UV",
      "스카이 오로라|DSQN2",
      "에스엠 광양|D7EF",
      "KOHSEI MARU|A8SJ3",
      "MANZANILLO|5LRV2",
      "PEGASUS GRACE|5LNE2",
      "에스엠 롱비치|D7FP",
      "SUNNY FREESIA|VRSS8",
      "MSC FLORIANA VI|5LLJ6",
      "XI YUAN|5LEG6",
      "ZHONG GU HANG ZHOU|BPCR7",
      "ALS HERCULES|CQ2132",
      "ONE REASSURANCE|9V3808",
      "에스엠 텐진|D7DG",
      "에스엠 얀티안|D7FS",
      "SM NINGBO|D7FG",
      "설퍼 브레이브|3FEK7",
      "케이에스 아너|224810",
      "티앤 이둔|D7AT",
      "세양프라임|180003",
      "우선호|DSFN9",
      "선 프린세스|250025",
      "RADIANT RAY|D5TH5",
      "타이하이 5|D7BW",
      "3현진호|172811",
      "DESERT SPRING|V7XQ8",
      "RUBINA|CQZG",
      "111효동케미|D7SJ",
      "유성호|130029",
      "WESTWOOD RAINIER|9V9003",
      "진양1호|184803",
      "DORIC TRIDENT|D5JY4",
      "오사카 보이저|D7AA",
      "REN JIAN 8|BPLL9",
      "팬콘 석세스호|DSRI7",
      "PRESIDENT CARTER|WPCW",
      "TIBERBORG|PCUC",
      "케이티에스그린|D7ZP",
      "써니 데이지|D7LL",
      "제이에스썬|230023",
      "NCC SAMA|HZFD",
      "거영썬3|D7LG",
      "제이앤 에메랄드|DSRK4",
      "티앤 레토|300TNLETO",
      "뉴 실버|D8SV",
      "UNIPOWER|3FAL8",
      "OCEAN CAPELLA|5LRZ9",
      "코리아비너스|D7SK",
      "HOEGH SEOUL|LADO6",
      "KIAN|9V6634",
      "GRANDE NAPOLI|IBZE",
      "HORIZON TRADER|DYTI",
      "ALDEN|LAXA8",
      "GREAT PANDA|3E6122",
      "BASTILLE STREET|A8YZ6",
      "에이원|130064",
      "SHUN FU DA|V7JS3",
      "RONGHE|A8ZS9",
      "MSC INES|3EFZ3",
      "CMA CGM NIAGARA|9HA4133",
      "ORIS|5VIS4",
      "GLORILAND|VRTS5",
      "이에스 로즈|088443",
      "성우제주|D7RO",
      "HARMONY 1|3E5300",
      "NEPTUNE LINE|3E3743",
      "MERGANSER|V7A6165",
      "ES FUTURE|3E7009",
      "그레이스 알파|192801",
      "우금호|DSIU5",
      "신성호|070606",
      "SETY|A8UZ4",
      "째즈|9V5491",
      "SHENG YUN 7|BOXF3",
      "엠에스클린|224814",
      "VARI TRADER|H3XM",
      "FUJI GALAXY|V7UF2",
      "BAR|4OCS",
      "GASCHEM BELUGA|CQ2873",
      "ASIA ASCEND|C6LB9",
      "KITHNOS|SVCH5",
      "디엘 다이아몬드호|DSPQ4",
      "ORCHID SYLT|V7PU7",
      "정진|160049",
      "TRANS FUTURE 8|3EZG6",
      "HONG RUN 16|5LHI7",
      "GAS POWER|3EVE2",
      "VISIO|A8CM9",
      "ALLEGRA|5LRT6",
      "HTK LOTUS|3WSY9",
      "MING YU 168|3E7078",
      "DEANA|V7A6181",
      "KEN REI|3EWK9",
      "JK GUNJANG|3EHP8",
      "KEN VISTA|3EYL6",
      "삼표3|180006",
      "EVA BRIGHT|3E4678",
      "TS HONOUR|V7HP8",
      "오션스프링|VRRP2",
      "에프씨 아도니스|V7B2983",
      "UOG GALINI|V7FU4",
      "천왕|240019",
      "유성|200013",
      "동남 에이스|240047",
      "동방7호|140035",
      "KEOYOUNG BLUE 3|HO9294",
      "BUENA ESPERANZA|3FQP5",
      "아르고스 레이|C6GU2",
      "CMA CGM HOPE|9HA5466",
      "MSC C MONTAINE|5LFC4",
      "XIN HAI TONG 810|5LFB7",
      "S SELIM|9HA6254",
      "COSCO SHIPPING LILY|VRXM3",
      "싸왓디 타일랜드|D7EE",
      "할라크|240017",
      "CELEBRITY MILLENNIUM|9HJF9",
      "송양1호|200009",
      "뉴 하모니|DSQJ9",
      "UNICORN OL|V7B3139",
      "루나 하나|DSFM6",
      "TATEV|3E8432",
      "GLORIWIND|VRDH9",
      "COOL GIRL|5BXJ6",
      "ULTRA KUROSHIO|HOA3374",
      "우성|192827",
      "두라썬|170035",
      "경성|210036",
      "우춘호|DSMS2",
      "SUN VENUS|3ECG6",
      "에프씨 글로리아|D7PG",
      "107효동케미|DSRG6",
      "글로리 하나|DSQU4",
      "제이앤 루비|D7IY",
      "NAVIGATOR CETO|D5HE5",
      "켐 하나|HO5909",
      "거영블루5|D7VA",
      "AAL DAMMAM|CQ2193",
      "NURI CHEMIST|3FHW3",
      "HUA LONG|3E8772",
      "제이에스 온산호|D8BV",
      "STOLT DISTRIBUTOR|VRIC3",
      "HANYU EMPIRE|DSQP2",
      "FUNENG 1|3E6905",
      "SSI DIGNITY|V7DC3",
      "17유성호|170036",
      "디케이 이토니아|D7HS",
      "제유호|970431",
      "LUCKY KOBE|3E8992",
      "ANNA M|D5ZO5",
      "에스티 스텔라|D7OY",
      "스쿠텀|D7TS",
      "그린 살바도르|5LMN7",
      "WECAN|D7XP",
      "HAKATA EXPRESS|3E7842",
      "써니 달리아|D7UA",
      "페가서스 테라|D7BH",
      "써니 클로버|D8FA",
      "PROGRESS|XVHR7",
      "스카이 제이드|V7ER5",
      "써니 아이비|VRTX9",
      "아트란틱 사우스|9V8010",
      "HONOR VOYAGER|3E3843",
      "HONOR BRIGHT|3E8847",
      "SUNNY LAVENDER|3FHO8",
      "YEOSU VOYAGER|3E4723",
      "챈나이 보야저|3E3614",
      "PACIFIC BUSAN|9V8001",
      "BELAWAN|VRCX3",
      "SAWASDEE SIRIUS|V7A5540",
      "KMTC INCHEON|3FHB3",
      "보스토치니 보이저|D8CM",
      "ZHONG GU PENG LAI|BQTK",
      "고베 트레이더|D7ID",
      "흥아 샤먼|D7ND",
      "STARSHIP URSA|V7ZR2",
      "센다이 트레이더|D7HW",
      "토야마 트레이더|5LLR8",
      "STARSHIP JUPITER|5LJL5",
      "SUNNY LAUREL|H8BZ",
      "SUNNY VIOLET|3E5968",
      "KYOWA EAGLE|V7A5912",
      "KMTC TAIPEIS|VRQQ3",
      "CA MANILA|VRWF4",
      "CLIPPER WILMA|LAGX8",
      "가연|181823",
      "SPIL NIKEN|3E3921",
      "요코하마 트레이더|D7GC",
      "HANSUNG INCHEON|D8BF",
      "TOKYO CAR|D5FF4",
      "DUKE CHEMIST|3EZZ6",
      "PANCON VICTORY|D7CC",
      "봉은호|120011",
      "PROVIDENT|3E3693",
      "제7천양|971467",
      "스카이 빅토리아|D8DJ",
      "창용1호|220023",
      "13대신호|130063",
      "우원호|200035",
      "HONOR GLORY|H9ZG",
      "스타보이저|D7FU",
      "팬스타 지니 2|D8RV",
      "다인3호|212803",
      "카리스 CHARIS|230007",
      "루비오션호|224816",
      "부광9호|230025",
      "5우영|230026",
      "제1한미르호|DSNA3",
      "BIG GEORGE|A8TR7",
      "ATLANTIC BRIDGE|9V7910",
      "GSL CHLOE|D5CE3",
      "KMTC PENANG|3ECW9",
      "EVER CONFORM|3E3441",
      "그린오션호|131062",
      "ITX EHIME|3FPM7",
      "SUNNY LILAC|3E5038",
      "ELENA|5IM597",
      "CONTSHIP WAY|5BFP5",
      "PROSRICH|J8TH8",
      "에스엠 자카르타|D7DP",
      "ACX DIAMOND|9VFL3",
      "EASLINE KWANGYANG|HOLT",
      "KMTC SINGAPORE|DSOA9",
      "스타 파이오니아|D7XJ",
      "21부영호|190026",
      "SKY FLOWER|3EUE6",
      "JIN SHUN HE|BPES2",
      "ORION|9LS2285",
      "EVGENIA|5IM886",
      "흥아영|D7GH",
      "ERASMUS FUTURE|3E7786",
      "스카이 프라이드|3E8435",
      "SEOUL GLOW|D5QC7",
      "페가서스 페타|D7ER",
      "HAO HAI JI YUN|3E5221",
      "페가서스 드림|DSAJ3",
      "ARICA BRIDGE|3FBA4",
      "PEARL RIVER BRIDGE|9V9638",
      "APL OCEANIA|KDAB",
      "포스요코하마|DSOU4",
      "포스 광저우|3E3870",
      "사왓디 리겔|V7A6129",
      "STARSHIP AQUILA|V7IQ5",
      "ONE CLARA|9VFW9",
      "ENDEAVOR TIDE|3E4746",
      "MAERSK NORESUND|3FCY9",
      "SEA OF LUCK|3FZM6",
      "뉴기니아 치프|VROO8",
      "HAI RUN SHENG DA|J5BG3",
      "스카이 문|V7ER6",
      "양쯔 트레이더|BPIT5",
      "동진 엔터프라이즈|D7PP",
      "JI YU|9LS2184",
      "삼원골드|030968",
      "HAINA PATRIOT|WDM3306",
      "티앤 루나|141076",
      "101효동케미호|021568",
      "GRAND WINNER 7|A8MR8",
      "청담|200033",
      "LADY BME|3E8496",
      "XINXIWANGMINGYUAN|V3IP",
      "VW PEACE|3FDF8",
      "BBC CITRINE|V2FY7",
      "SILVER SAILING|VRIH8",
      "BOW OLYMPUS|LAFY8",
      "KMTC SHIMIZU|D5YE8",
      "DE MI|S9Z1",
      "HIBIKI|3E5367",
      "나고야 트레이더|D8TG",
      "DAEJOO ARIRANG 2|3EZP2",
      "승진|230047",
      "미래3호|111844",
      "9민성호|161822",
      "ATLANTIC PIONEER|9V7919",
      "XINQUNDAO|H3OI",
      "SHAO YUN|BPOB2",
      "HE YUAN 1|3E3956",
      "XIN MING ZHOU 20|BPNA5",
      "XING PING|VREG9",
      "HONOR PROSPER|3E8762",
      "YA LU JIANG|BPJR2",
      "상아호|151819",
      "CONTRIVIA|V7A4978",
      "ZHONG SHENG TUO HAI|6YXV7",
      "TS TOKYO|V7DU4",
      "XIN HE DA|3FMT9",
      "CONSISTENCE|V7A4450",
      "포스 싱가포르|5LOD9",
      "SITC SHENGDE|VRUY7",
      "팬콘 챔피언|D7SP",
      "거제유비아|180005",
      "동방에이스호|133507",
      "SM JEJU LNG2|3ESH2",
      "거제 이션|D7DI",
      "로얄삼부|D7CV",
      "HONGLI|BOSP6",
      "거영 스타 5|D7KS",
      "럭키오션호|204007",
      "CHANG DA 368|V3QM3",
      "ZI DING XIANG|BPKY8",
      "PACIFIC TIANJIN|9V8011",
      "36한진호|202809",
      "7대복|170030",
      "3명광호|200031",
      "제1거양|950536",
      "21동방호|210003",
      "EVER CROWN|3EEF9",
      "아람|176801",
      "11송원호|130037",
      "흥아 아키타|D7MT",
      "REN JIAN 25|BQQR",
      "써니팜호|DSEK8",
      "SUNNY ORCHID|3E8387",
      "우진1호|060821",
      "거영 블루 7|D7XD",
      "VLADIMIR BIRYUKOV|UBFY7",
      "동방3호|120021",
      "7보광호|130088",
      "68세한호|222801",
      "트리톤|160031",
      "KAIROS|VRYA6",
      "BLUE KINGDOM|3FLI8",
      "MC HERA|5LTW2",
      "PRINCESS IRIS|9V2137",
      "MING PING|V3BJ3",
      "백경호|146804",
      "한유파이오니아|150035",
      "ZENITH GLORY|3EDY8",
      "한성9호|965128",
      "BLUE WHALE|5LJR5",
      "일신그린아이리스|DSJA6",
      "TS INDEX|V7QU5",
      "IRIS CORAL|3E7177",
      "CORAL ACROPORA|PCIG",
      "SUN DAHLIA|V7A2621",
      "라이징 삼부|D7TR",
      "308 HYODONG CHEMI|D7UZ",
      "에스티 프레야|300STFR",
      "PACIFIC MONACO|9V7999",
      "에스제이아너호|DSRB4",
      "TIGER CHENNAI|9V8713",
      "ESL KABIR|CQ2099",
      "ESL ASANTE|CQOP",
      "ZHONG WAI YUN SHEN ZHEN|BOBO6",
      "NEW DRAGON|5LKO8",
      "MATAKANA ISLAND|VRGM4",
      "포스 람차방|5LOE2",
      "MCC SHENZHEN|V2GK7",
      "WOOHYUN HOPE|DSQQ4",
      "JI YONG|3E8459",
      "우리 하나|D7WH",
      "EVER CALM|H3OA",
      "제8에스제이가스|D7CI",
      "MU DAN YUAN|BPEF2",
      "가스브로드웨이|DSQT6",
      "YU CHANG 128|3E2180",
      "홍진호|092615",
      "CORAL ACTINIA|PBUC",
      "SPRING MOTA|VRQU8",
      "서해제일1호|221827",
      "HAPPY LEADER|3FIP7",
      "한유누리|170009",
      "MERATUS JAYAGIRI|3E4972",
      "BRIGHT MOON|3E8325",
      "VAST OCEAN|5LFT9",
      "다온|224805",
      "YONG SHENG 158|3E2538",
      "NDL SIX|TYG18",
      "자카르타 보이저|D7JE",
      "KMTC QINGDAO|DSQT9",
      "SITC JUNDE|VRWA5",
      "스카이 티아라|3E3872",
      "티와이 인천|D8TI",
      "오성3호|181056",
      "VALIANT|3EBG4",
      "YUN HAI MIN SHENG|3E8450",
      "RONNIE|V2HJ4",
      "포세이돈|161047",
      "제니스 그레이스|231023",
      "XIN TAI PING|BSDU",
      "GUANG TONG 15|3E2567",
      "TIAN EN 2|3E2619",
      "3영호|008346",
      "HUA YUN 1|V3VQ6",
      "GAIN SPRING|3E4671",
      "KAIROS TRIUMPH|D5KW6",
      "HYUNDAI MASAN|V7UY6",
      "AYANA SMILE|DYHY",
      "ZENITH OCEAN|3E8488",
      "PETROLIMEX 09|3WPG",
      "뉴 챌린지호|DSQA4",
      "에이치와이 광양|240001",
      "NING FENG LENG 16|BQBK7",
      "DONGJIN GENIUS|D7PC",
      "두라7|111002",
      "이스턴 비너스|3E7469",
      "대진8001|120050",
      "HANSUNG WEIHAI|3E8662",
      "팬콘 선샤인|D7CO",
      "홍콩 보이저|D7BC",
      "스타 익스플로러|V7A2844",
      "SONG YUN HE|3FRF8",
      "MOJI EXPRESS|3E8451",
      "재원 니케|190013",
      "REN HE|V3UW2",
      "에스제이글로리호|DSFA",
      "ROTTERDAM TRADER|V2GN7",
      "PACIFIC NINGBO|9V8013",
      "HF WEALTH|VRTL4",
      "PROSPER|5IM811",
      "대성5호|968921",
      "아사카|D7BR",
      "SUNNY CAMELLIA|VRNZ6",
      "JIA LONG|V3PP",
      "제301삼영호|HLLN",
      "GENERAL TROSHEV|UAJO",
      "ZALIV ZABIYAKA|UEAJ",
      "대성102호|950023",
      "ALIOT|UBBE",
      "해누리|D7YA",
      "티엔에스 캐쳐|D7UO",
      "WOOYANG LEADER|3FNI2",
      "ISLAND SKY|C6TQ2",
      "RUI YANG 7|S9A8",
      "해원호|121835",
      "뉴 그랜드 피스|H3OX",
      "동방루비|242817",
      "SUNNY KALMIA|3E8980",
      "A ROKKO|VRVY3",
      "모닝 빅토리호|170024",
      "HAFNIA YARRA|9V3759",
      "에스에스 루나|D9AC",
      "퓨쳐 아시아 1|3FUN2",
      "WOOYANG GLORY|D7EB",
      "ZENITH VICTORY|3E9007",
      "오션가스호|D7VU",
      "아시아가스호|D7BU",
      "THANG LONG GAS|XVDB7",
      "MARI INNOVATOR|LALK8",
      "DREAM|D5YS3",
      "MAGNA|C6TN2",
      "스타챌린저|D7CH",
      "INTERASIA TACTIC|9V9142",
      "VICTORIA|V7LN2",
      "ALAMOSBORG|PCMV",
      "SCS STAR|UBEI3",
      "브리지워터 디스커버리|E6CN3",
      "ANGEL BLUE|3FBF6",
      "지 위즈덤|134806",
      "ZUIHO MARU|7JQW",
      "씨가스|D8DX",
      "BUENA LUNA|3FTH3",
      "CRANE VEGA|H3VB",
      "XIN HAI 131|V3ND9",
      "ESMERALDA|9V7559",
      "HAFNIA AQUAMARINE|9V8440",
      "TORERO|3E7418",
      "마린가스|DSEZ7",
      "우동|D7BN",
      "TONG XIN YUAN|BOOA",
      "BUENA SUERTE|3FXP5",
      "GAS FRONTIER|3E8838",
      "레이디가스|DSRP5",
      "GAS ELEGANCE|3EOM3",
      "금향호|130024",
      "노바|D7LI",
      "화정에이스|202813",
      "레이크 오로라|D7UQ",
      "HONG TAI 216|3E2788",
      "HE HUI 12|BPDN8",
      "싸왓디 선라이즈|D7HY",
      "동진 엔듀런스|D7ZY",
      "XIN XIANG LI 56|BPPF3",
      "CRANE URANUS|3FMN5",
      "CRANE REGULUS|HONQ",
      "드래곤스카이|DSNB9",
      "코롤1호|DSNG8",
      "미라클 알파|151058",
      "SUN SIRIUS|3FNA8",
      "TORVANGER|LAMJ7",
      "와이엔 광양|D7TX",
      "씨에스 오션|3E8686",
      "SILVER LEO|3FJT4",
      "NING HUA 432|BOAU9",
      "GLOBAL FLORA|3ETQ2",
      "TAKAROA SUN|9V6745",
      "XIN HAI 799|3E8769",
      "JIN DONG 9|S9Z16",
      "리치 세일링|V3PV8",
      "케이에스 썬글로리|D7WR",
      "미래9호|102740",
      "스카이 호프|DSAC3",
      "삼표 1|170037",
      "신정601호|920411",
      "RISUN 16|6YWZ8",
      "제니스 퀸|D7FJ",
      "SHANG HUA|9LU2920",
      "티와이 글로리아호|DSQJ2",
      "JIN YANG|3ENO5",
      "에스티 벨라|D7DM",
      "BS DAESAN|D7QL",
      "GRAND MUSE|HO6237",
      "ADDISON|D5MB8",
      "YUAN XIANG FEN JIN|3E7460",
      "HONOR OCEAN|3E3839",
      "에스제이 엔젤|DSRB5",
      "MING HONG|V3BX2",
      "JIANG YUAN YUAN DA|BOQA9",
      "HENG HE|V3ZX",
      "DK IMAN|D8DC",
      "광양 썬샤인호|DSHP6",
      "에이치와이 부산|210043",
      "거영스타3|D7RJ",
      "ZENITH ACE|3E6645",
      "1명광호|240029",
      "8001|CSB8001",
      "HONG YANG|V3GC2",
      "JINHUA 15|J5AW2",
      "YU DE|VRWI8",
      "TAURUS|DSQW7",
      "디케이 아이웨이|D7EN",
      "TONG CHENG 198|V3NA",
      "DYNAWAY PIONEER|3E3763",
      "LIAN YUN 9|9LU2481",
      "선진호|211802",
      "XIN HAI 79|3E8314",
      "웨스트 카페리|062928",
      "TS MELBOURNE|V7A7350",
      "백령 153호|171825",
      "XIN HAI 59|J5AU1",
      "HIROTO|V3AE",
      "HAO XIN|V3MW4",
      "JIN HUA|3ESJ9",
      "ZENITH GREEN|3E8925",
      "GLOBAL STAR|9V7049",
      "YING XIN|V3HU2",
      "HALLA FRONTIER|050626",
      "티와이해피|D7SS",
      "XI YUN|V3MX2",
      "SHORYU 3|HOA7205",
      "MING XI|V3LM2",
      "PU REN|V3CY3",
      "비엔알2000호|166807",
      "PANSTAR MIRACLE|HOA5934",
      "지민101|230034",
      "파라미타|S9A3142",
      "아키타 트레이더|5LLR9",
      "써니 아카시아|D7NE",
      "AS PATRIA|CQIX5",
      "단양|DSQA3",
      "두라 5|180020",
      "오션 프라이드 원|D6A4061",
      "JI PENG|H3RB",
      "인트란스 에디|141033",
      "BOW EXCELLENCE|LAYP4",
      "썬 에델바이스|V7A2776",
      "SUSANOO|V7A3541",
      "PRINCESS AMBER|3EDK5",
      "XIN HONG XING 229|3E6752",
      "TEN JUPITER|3E8470",
      "강남호|885116",
      "AN DONG 68|BTDW",
      "SM JEJU LNG1|3FTI8",
      "GOLDEN CYGNUS|9V6167",
      "제2승한호|975981",
      "KMTC PUSAN|DSFT8",
      "제6대성호|940514",
      "두라스카이|180010",
      "팬스타 지니|D8FB",
      "드레넥|9HB2079",
      "WELLINGTON STAR|C6TJ9",
      "PONGA|3E7853",
      "CRYSTAL AFRICA|UBGF6",
      "AZALEA|3EFG6",
      "대성201호|080122",
      "보넨자|DSPF9",
      "우승호|242826",
      "골든 오스트라리스|9V5189",
      "GUANG TONG 33|3E7270",
      "제니스 부산|092219",
      "PACIFIC SINGAPORE|9V7740",
      "FORTUNE 8|9LU2611",
      "YUAN ZHENG|9LU2546",
      "BS NGHI SON|D8HX",
      "포천 카렌|D8BU",
      "대성202호|046546",
      "일신프린세스 로얄|106783",
      "대한1호|DSOD5",
      "광양 프론티어|3E8749",
      "티와이 메리|D7TO",
      "코리아 케미|D7AD",
      "ARDMORE SEAWOLF|V7JZ7",
      "자이언트 삼부|DSPL3",
      "본아미|6KSG",
      "한반도|D7RH",
      "아약스|UBIZ7",
      "EASTERN TRITON|5LQC9",
      "거영스타호|DSPH2",
      "안성201호|062974",
      "우찬|161008",
      "케이티에스 실버|D7TM",
      "썬퀸|H9HG",
      "GOLDEN GLORY|3EZT8",
      "CRANE MAIA|3ESK6",
      "티와이 에버호|DSPF4",
      "성진3호|050481",
      "서해15호|999018",
      "103 성신호|DSDU4",
      "강남티 9호|960625",
      "뉴 카멜리아|JG5720",
      "제11쌍용|161001",
      "한미르|D7TQ",
      "MIR HANA|3E6941",
      "RONG KAI|HOA2618",
      "XIN FENG HAI|3FYN5",
      "RUN KAI|HOA4554",
      "아라온 ARAON|DSQL7",
      "한나래호|D7VW",
      "BRIGHT SUN|3E8393",
      "금양3호|DSAU",
      "BASAR|V3VD3",
      "YEONSUNG|DSQY5",
      "수성7|DSFJ2",
      "은호|886630",
      "골든 조이 하나호|D8CS",
      "그레이스삼부|DSPD6",
      "202고려호|DSGR",
      "625 덕양|080444",
      "대진8006|170004",
      "108대양호|079991",
      "901조양|DSFB",
      "EGS SURVEYOR II|3FMM5",
      "수성5|DSFJ4",
      "젬 라토야|V7A3474",
      "아그네스90|6LZM",
      "연성88호|241811",
      "207동성호|962050",
      "103 효동케미|D7MJ",
      "20청우호|202823",
      "HUI JI|T8A3940",
      "JINHUA 11|J5BE1",
      "일성103호|954516",
      "HONG QIAO|9LS2189",
      "탐사호|224806",
      "선우자이언트호|932171",
      "EURO STAR|3EJQ3",
      "101성신호|DSOA2",
      "스카이로얄|130095",
      "태림재스민호|DSPF5",
      "수성3|040491",
      "씨플라워|DSJA4",
      "팬스타 쓰시마 링크|D7DZ",
      "넘버투 조초|D7JO",
      "울산705호|039076",
      "NAZIMOV|UBIZ3",
      "77삼영호|DSGZ",
      "노빅|UBIZ4",
      "ULTIMATE|UCPG",
      "BUKHTA ASACHA|UHJK",
      "RINA SEA|6YWG7",
      "BAKLANOVO|UGBT",
      "해진|D7RF",
      "제101삼일호|071203",
      "신시지 112|BZV5N",
      "BIKIN|UBCH",
      "KIBENA 1|T3FQ",
      "프레가트|UBRW5",
      "블루오션|244807",
      "골든 그레이스 하나|3E3399",
      "우진 파이오니어호|DSNH2",
      "GRACE SULPHUR|3EYQ5",
      "필로스 1|160028",
      "XUAN JING|BPPV2",
      "ORIENTAL PEARL VIII|3FTX3",
      "유진1호|073141",
      "제물포2호|882285",
      "이코노스타|782385",
      "수경호|070890",
      "선라이즈 삼부|DSNR6",
      "티와이아이리스호|DSOY4",
      "JINHUA 9|J5BE8",
      "12한진호|132825",
      "ALLIANCE NO 2|T8A4488",
      "NO 102 KUM YANG|6LZQ",
      "KAMLAYN|UDRM",
      "아틀란트|UBJT8",
      "ECOPACIFIC|UBRX",
      "삼양505호|954325",
      "15선영호|150012",
      "현대 당진|070592",
      "신향설란|BOLV4",
      "NEW GOLDEN BRIDGE V|HPUO",
      "SUN LORD|3EUS5",
      "성희호|DSFS8",
      "FU YUAN YU 8295|BZW7N",
      "FU YUAN YU 8299|BZW2O",
      "FU YUAN YU 8298|BZW1O",
      "7세윤호|202810",
      "강남101호|969070",
      "에스앤비1호|032583",
      "1003종영호|021285",
      "수성2|DSFV3",
      "대성101호|100933",
      "건룡호|170014",
      "유쇼 마루|7KNG",
      "오션에이스 2호|122820",
      "메가 파이오니아호|DSPZ6",
      "한진3007호|086790",
      "명진호|130047",
      "광양12호|085633",
      "근양|DSQK5",
      "대성7호|D8WQ",
      "105성신호|969115",
      "SD GLORIA|HOKX",
      "강남T 13호|942504",
      "AKIMOTO|9LS2091",
      "해신102|181814",
      "금오티1호|031342",
      "부강1|244401",
      "광진월드3호|D7YK",
      "광성호|151802",
      "32대영호|130010",
      "302종영호|920665",
      "유진|160019",
      "101신동|220009",
      "202대양호|042092",
      "덕양5001호|060181",
      "대성8001|080193"
    ],
    "by_normalized_vessel_name_gt_vessel_type": [
      "MINERAL HOPE|91971|BULK CARRIER",
      "MARCEL|44102|BULK CARRIER",
      "BERGE DOI INTHANON|36177|BULK CARRIER",
      "BEI HAI FENG HUANG|43551|CRUDE TANKER",
      "CF DIAMOND|32378|BULK CARRIER",
      "VITUS BERING|66291|BULK CARRIER",
      "PAN PEGASUS|43958|BULK CARRIER",
      "ERSOZ WEST|36332|BULK CARRIER",
      "에이치엘 오셔닉|97574|BULK CARRIER",
      "ORION TRADER|35908|BULK CARRIER",
      "FIONAN|62272|BULK CARRIER",
      "스키야토스|109299|BULK CARRIER",
      "HL PORT HEDLAND|93461|BULK CARRIER",
      "KOBAYASHI MARU|34552|BULK CARRIER",
      "CHANG HANG HU PO|31530|TANKER",
      "WASHINGTON|62318|CRUDE TANKER",
      "CONDOR|12085|TANKER",
      "SAKURA CRESCENT|54281|BULK CARRIER",
      "GENCO STARS AND STRIPES|107879|BULK CARRIER",
      "ONE TREASURE|210691|CONTAINER SHIP",
      "DHT REDWOOD|161511|CRUDE TANKER",
      "한유울산|1996|TANKER",
      "CORAL ALICIA|6288|GAS CARRIER",
      "MSC FAITH|140976|CONTAINER SHIP",
      "MSC IVANA|131771|CONTAINER SHIP",
      "세양글로리|1909|TANKER",
      "PRISM COURAGE|122166|GAS CARRIER",
      "에이치엘 그린|97545|BULK CARRIER",
      "OMAHA|91775|BULK CARRIER",
      "FPMC C MELODY|156975|CRUDE TANKER",
      "NAVE ALLEGRO|160115|CRUDE TANKER",
      "FRONT SPEY|160737|CRUDE TANKER",
      "ARDMORE PURSUIT|29455|CRUDE TANKER",
      "23부광호|298|TANKER",
      "HMM TURQUOISE|126943|CONTAINER SHIP",
      "스카이 글로리|5534|BULK CARRIER",
      "스카이케미|1772|TANKER",
      "MSC MIRJAM|193489|CONTAINER SHIP",
      "MSC ALESSIA|155104|CONTAINER SHIP",
      "OLYMPIC TRUST|170611|CRUDE TANKER",
      "EAGLE VELLORE|156186|CRUDE TANKER",
      "FMG AMANDA|134693|BULK CARRIER",
      "PUTERI SEJINJANG|110331|GAS CARRIER",
      "WOOYANG ARES|35332|BULK CARRIER",
      "SEAMERIDIAN|30241|CRUDE TANKER",
      "LIA|42010|TANKER",
      "디엘 앰버|7333|TANKER",
      "우혁|5025|TANKER",
      "SEA PEARL|154381|CRUDE TANKER",
      "씨 챌린저|166381|CRUDE TANKER",
      "KN BLOSSOM|44375|BULK CARRIER",
      "PACIFIC MOONSTONE|30087|TANKER",
      "STI CONNAUGHT|64827|TANKER",
      "NEW SOLUTION|162198|CRUDE TANKER",
      "ANDES|39085|TANKER",
      "NAVIOS INDIGO|39906|CONTAINER SHIP",
      "에이치엠엠 방콕|75308|CONTAINER SHIP",
      "HMM TOPAZ|126943|CONTAINER SHIP",
      "ROMANCE|30964|TANKER",
      "MORNING LADY|70834|PCTC",
      "FLORA MARIS|30964|CRUDE TANKER",
      "BELFUTURE|36139|BULK CARRIER",
      "ASIA VISION|101427|GAS CARRIER",
      "CMA CGM MONACO|71706|PCTC",
      "MSC VALENTINA|155492|CONTAINER SHIP",
      "MSC TINA|194308|CONTAINER SHIP",
      "MSC TESSA|236078|CONTAINER SHIP",
      "MSC ANNAMARIA|155104|CONTAINER SHIP",
      "MSC METTE|235651|CONTAINER SHIP",
      "HYUNDAI VOYAGER|52581|CONTAINER SHIP",
      "SEA ORCA|64293|TANKER",
      "ALEXANDRA|43041|BULK CARRIER",
      "TEAL BULKER|32370|BULK CARRIER",
      "MILAGRO|40298|BULK CARRIER",
      "MORNING SALUTE|49799|BULK CARRIER",
      "MARAN GAS ANTIPAROS|115118|GAS CARRIER",
      "MAY|41662|BULK CARRIER",
      "MAR CAMINO|30454|BULK CARRIER",
      "ELEKTRA|67264|PCTC",
      "글로벌 파이오니어|107700|BULK CARRIER",
      "UBUNTU SINCERITY|102039|BULK CARRIER",
      "DANAE R|38888|BULK CARRIER",
      "DIAMANTINA|43024|BULK CARRIER",
      "F SUN|93152|BULK CARRIER",
      "PAN IRIS|92370|BULK CARRIER",
      "SEABEAUTY|108551|BULK CARRIER",
      "LYDIA OLDENDORFF|107553|BULK CARRIER",
      "LUCY OLDENDORFF|92722|BULK CARRIER",
      "PAN COSMOS|106510|BULK CARRIER",
      "HAFNIA ALMANDINE|23676|TANKER",
      "한남|1097|TANKER",
      "ASIA SPRING|39994|BULK CARRIER",
      "GLOBAL HOSPITALITY|32384|BULK CARRIER",
      "MISSION REVIVAL|32431|BULK CARRIER",
      "MSC BELLISSIMA|171598|CRUISE SHIP",
      "CMA CGM SYMI|150844|CONTAINER SHIP",
      "아프리칸 스타링|31751|BULK CARRIER",
      "PATHFINDER|51917|PCTC",
      "HIGH MARINER|30523|TANKER",
      "CHANG HANG FEI CUI|31534|TANKER",
      "SOLAR KAREN|30259|TANKER",
      "FLAG ZANNIS|43767|BULK CARRIER",
      "KMARIN RESOLUTION|64309|CRUDE TANKER",
      "NAVE POLARIS|63398|TANKER",
      "SAPPHIRE ETERNITY|36002|BULK CARRIER",
      "FEDERAL ILLINOIS|35833|BULK CARRIER",
      "피갈리아 나비게이터|44668|BULK CARRIER",
      "SARA|43735|BULK CARRIER",
      "YASA LEOPARD|62716|TANKER",
      "SEAODYSSEY|64092|TANKER",
      "뉴동신호|299|TANKER",
      "타히티|430|TANKER",
      "HMM EMERALD|126995|CONTAINER SHIP",
      "흥아 하이퐁|9998|CONTAINER SHIP",
      "CLIFFORD MAERSK|92198|CONTAINER SHIP",
      "AC VICTORY|38871|BULK CARRIER",
      "GT ATHENA|41320|BULK CARRIER",
      "HMM BLESSING|114023|CONTAINER SHIP",
      "YM TUTORIAL|118523|CONTAINER SHIP",
      "SEASPAN PRIDE|141823|CONTAINER SHIP",
      "COCHRANE|94895|CONTAINER SHIP",
      "ZIM WILMINGTON|94784|CONTAINER SHIP",
      "MSC ANTIGUA|94453|CONTAINER SHIP",
      "SAN FERNANDO|97367|CONTAINER SHIP",
      "MANZANILLO EXPRESS|123560|CONTAINER SHIP",
      "GSL NINGBO|89097|CONTAINER SHIP",
      "MSC LILY|96333|CONTAINER SHIP",
      "에이치엠엠 리프|86290|CONTAINER SHIP",
      "신정3호|237|TANKER",
      "비케이 25|427|TANKER",
      "WAN MING HE XIE|28194|BULK CARRIER",
      "SILK JAKARTA|39941|CONTAINER SHIP",
      "DIAMOND PRINCESS|115906|CRUISE SHIP",
      "씨호라이즌호|1599|TANKER",
      "ADORA MAGIC CITY|136201|CRUISE SHIP",
      "MSC EMMA|141649|CONTAINER SHIP",
      "STAR STAMFORD|34447|BULK CARRIER",
      "스카이마스|858|TANKER",
      "SEASPAN BRAVO|113042|CONTAINER SHIP",
      "CMA CGM PLATINUM|128060|CONTAINER SHIP",
      "LIBERTY PASSION|58107|PCTC",
      "글로비스 세이프티|72376|PCTC",
      "ONE WREN|146409|CONTAINER SHIP",
      "CMA CGM BUZIOS|129503|CONTAINER SHIP",
      "YM UNANIMITY|90532|CONTAINER SHIP",
      "CMA CGM HYDRA|128600|CONTAINER SHIP",
      "ONE COMPETENCE|87035|CONTAINER SHIP",
      "OOCL UTAH|92111|CONTAINER SHIP",
      "ONE SPARKLE|139588|CONTAINER SHIP",
      "SEASPAN ADONIS|106154|CONTAINER SHIP",
      "ONE COSMOS|88089|CONTAINER SHIP",
      "ZENITH LUMOS|149525|CONTAINER SHIP",
      "LE HAVRE|108069|CONTAINER SHIP",
      "VIENNA EXPRESS|93750|CONTAINER SHIP",
      "NEW FIRST|25759|BULK CARRIER",
      "ETHANE CORAL|60199|GAS CARRIER",
      "STOLT LOTUS|22424|TANKER",
      "BW TOKYO|47985|GAS CARRIER",
      "GLOVIS TREASURE|77560|PCTC",
      "STAR LYSEFJORD|37447|BULK CARRIER",
      "라피스 어로우|41000|PCTC",
      "DMC JUPITER|14948|GENERAL CARGO",
      "NBA MONET|43013|BULK CARRIER",
      "TOSCANA|61328|PCTC",
      "NOCC PACIFIC|68903|PCTC",
      "해창썬|1154|TANKER",
      "ADORA MEDITERRANEA|85619|CRUISE SHIP",
      "GRAND DAHLIA|59217|PCTC",
      "EPSON TRADER|34728|BULK CARRIER",
      "GLOVIS COMET|55680|PCTC",
      "CMA CGM CASSIOPEIA|131332|CONTAINER SHIP",
      "GNS HARVEST|40042|BULK CARRIER",
      "TORM EVA|42208|TANKER",
      "NAVIG8 MESSI|43904|TANKER",
      "CHALLENGE PRELUDE|28823|TANKER",
      "LILAC VICTORIA|40976|TANKER",
      "부광5호|1162|TANKER",
      "MAERSK SARNIA|93511|CONTAINER SHIP",
      "에스제이 호프|5667|TANKER",
      "OOCL SINGAPORE|141712|CONTAINER SHIP",
      "PARANA|47053|PCTC",
      "케이엠티씨 선전|28827|CONTAINER SHIP",
      "우현|1975|TANKER",
      "POAVOSA ACE|17027|BULK CARRIER",
      "JN JUPITER|11733|TANKER",
      "성호 에이스호|8577|TANKER",
      "PALMELA|55926|PCTC",
      "페트리어트|60979|PCTC",
      "MORNING PRIDE|65424|PCTC",
      "테르모필레|75283|PCTC",
      "타이판|57692|PCTC",
      "ORCA PEARL|59408|CRUDE TANKER",
      "CRYSTAL RAY|57772|PCTC",
      "LAKE TAZAWA|71631|PCTC",
      "PAGANELLA|47020|PCTC",
      "CMA CGM MONZA|71631|PCTC",
      "AURORA GUARDIAN|49561|GAS CARRIER",
      "AKSEL|62775|TANKER",
      "ORIENTAL PARALLEL|9780|BULK CARRIER",
      "LOCH LONG|43083|BULK CARRIER",
      "NOBLE ACE|59515|PCTC",
      "ABRACADABRA|34508|BULK CARRIER",
      "HSL VEGAS|44140|BULK CARRIER",
      "WEI LUN JU LONG|43717|BULK CARRIER",
      "AGIA SOFIA I|44192|BULK CARRIER",
      "STAR ATLAS|43978|BULK CARRIER",
      "HYUNDAI OCEANPIA|113998|GAS CARRIER",
      "PROGRESS ACE|57789|PCTC",
      "TURQUOISE ACE|77695|PCTC",
      "PAN MAJESTY|36474|BULK CARRIER",
      "SHANGHAI HIGHWAY|48927|PCTC",
      "WOOYANG BANDERS|40230|BULK CARRIER",
      "GALAXY GLOBE|44069|BULK CARRIER",
      "XIN CANG ZHOU|47917|CONTAINER SHIP",
      "펜타|40043|BULK CARRIER",
      "SERI AYU|95729|GAS CARRIER",
      "VIKTOR TSOI|40972|BULK CARRIER",
      "MARAN GAS LINDOS|103893|GAS CARRIER",
      "카라호|1843|BULK CARRIER",
      "OCEAN FUTURE|31532|BULK CARRIER",
      "호프 만|30002|BULK CARRIER",
      "OSLO VENTURE|36336|BULK CARRIER",
      "케이티에스 화이트|2101|TANKER",
      "HAFNIA TAGUS|43072|CRUDE TANKER",
      "부양에이스|415|TANKER",
      "YM TARGET|115761|CONTAINER SHIP",
      "EVER FORWARD|117340|CONTAINER SHIP",
      "에코 가스|998|GAS CARRIER",
      "티앤 레아|1912|TANKER",
      "BW CARINA|47342|GAS CARRIER",
      "NBA MILLET|43008|BULK CARRIER",
      "G DOLCE|47558|GAS CARRIER",
      "SANSOVINO|47347|GAS CARRIER",
      "VALLEE BLANCHE|49640|GAS CARRIER",
      "HENG XING FA ZHAN|28105|BULK CARRIER",
      "ENERGY NAVIGATOR|118842|GAS CARRIER",
      "프리티 프로스페리티|27662|BULK CARRIER",
      "광산|268|TANKER",
      "유한1호|337|TANKER",
      "우진|5197|TANKER",
      "제7현진호|339|TANKER",
      "HU PO|61724|TANKER",
      "제8우진호|297|TANKER",
      "ENSENADA|66332|CONTAINER SHIP",
      "KMTC ULSAN|16717|CONTAINER SHIP",
      "SINOKOR NIIGATA|6490|CONTAINER SHIP",
      "MSC JERSEY|47873|CONTAINER SHIP",
      "INTERLINK SOLIDITY|25546|BULK CARRIER",
      "MISSOURI EXPRESS|75579|CONTAINER SHIP",
      "XIN TIAN JIN|66433|CONTAINER SHIP",
      "XING YU 68|13266|BULK CARRIER",
      "케이엠티씨 제벨 알리|40898|CONTAINER SHIP",
      "MSC UNITE VI|69218|CONTAINER SHIP",
      "HYUNDAI SUPREME|52581|CONTAINER SHIP",
      "SEASPAN RIO DE JANEIRO|39941|CONTAINER SHIP",
      "SEASTAR HAWK|24439|BULK CARRIER",
      "MELBORNE BRIDGE|75154|CONTAINER SHIP",
      "STOLT CAPABILITY|24625|TANKER",
      "CS HANA|5273|TANKER",
      "STOLT VOYAGER|2761|TANKER",
      "HANSA SEALANCER|26897|CRUDE TANKER",
      "EAGLE ASIA 11|6234|TANKER",
      "슈퍼 이스턴|8231|TANKER",
      "로터스 삼부|5598|TANKER",
      "SEAWAYS WARWICK|29767|TANKER",
      "VOYAGER|20117|TANKER",
      "TORM THUNDER|29609|TANKER",
      "ORIENTAL SUNSTONE|29774|TANKER",
      "GREAT WHITE|29266|TANKER",
      "TORM TIMOTHY|29609|TANKER",
      "우황|5197|TANKER",
      "미시칸|5372|TANKER",
      "OAK EXPRESS|28985|CRUDE TANKER",
      "한유 빅토리아|5074|TANKER",
      "아시안 그레이스|5988|TANKER",
      "PETREL PACIFIC|29403|CRUDE TANKER",
      "HAFNIA PANTHER|29737|TANKER",
      "SUN MERCURY|7294|TANKER",
      "우림 5|8072|TANKER",
      "CL YINGDU|29455|TANKER",
      "STOLT AJISAI|7242|TANKER",
      "CLYNELISH|11944|TANKER",
      "JIN HANG 89|5660|BULK CARRIER",
      "CHANG HANG ZUAN SHI|31534|TANKER",
      "THE PROSPECTOR|10830|TANKER",
      "STI ESLES II|29804|TANKER",
      "MITSUI OCEAN FUJI|32477|CRUISE SHIP",
      "MSC ALYSSA|43575|CONTAINER SHIP",
      "동진 피데스|7683|CONTAINER SHIP",
      "스카이 오로라|5500|BULK CARRIER",
      "에스엠 광양|74962|CONTAINER SHIP",
      "KOHSEI MARU|2987|케미칼 운반선",
      "MANZANILLO|38928|BULK CARRIER",
      "PEGASUS GRACE|9908|CONTAINER SHIP",
      "에스엠 롱비치|74962|CONTAINER SHIP",
      "SUNNY FREESIA|9527|CONTAINER SHIP",
      "MSC FLORIANA VI|69947|CONTAINER SHIP",
      "XI YUAN|40060|GENERAL CARGO",
      "ZHONG GU HANG ZHOU|54466|CONTAINER SHIP",
      "ALS HERCULES|73360|CONTAINER SHIP",
      "ONE REASSURANCE|74063|CONTAINER SHIP",
      "에스엠 텐진|42110|CONTAINER SHIP",
      "에스엠 얀티안|75061|CONTAINER SHIP",
      "SM NINGBO|74962|CONTAINER SHIP",
      "설퍼 브레이브|3887|케미칼 운반선",
      "케이에스 아너|7057|TANKER",
      "티앤 이둔|1877|TANKER",
      "세양프라임|1974|케미칼 운반선",
      "우선호|1716|TANKER",
      "선 프린세스|1984|케미칼 운반선",
      "RADIANT RAY|11918|TANKER",
      "타이하이 5|3038|케미칼 운반선",
      "3현진호|208|TANKER",
      "DESERT SPRING|33631|GENERAL CARGO",
      "RUBINA|25618|BULK CARRIER",
      "111효동케미|2101|TANKER",
      "유성호|549|TANKER",
      "WESTWOOD RAINIER|32551|CONTAINER SHIP",
      "진양1호|1995|TANKER",
      "DORIC TRIDENT|32370|BULK CARRIER",
      "오사카 보이저|7447|CONTAINER SHIP",
      "REN JIAN 8|41899|CONTAINER SHIP",
      "팬콘 석세스호|9892|CONTAINER SHIP",
      "PRESIDENT CARTER|59052|CONTAINER SHIP",
      "TIBERBORG|14695|GENERAL CARGO",
      "케이티에스그린|2328|TANKER",
      "써니 데이지|9867|CONTAINER SHIP",
      "제이에스썬|1119|TANKER",
      "NCC SAMA|29191|TANKER",
      "거영썬3|610|TANKER",
      "제이앤 에메랄드|4067|TANKER",
      "티앤 레토|2650|TANKER",
      "뉴 실버|8504|TANKER",
      "UNIPOWER|8081|GENERAL CARGO",
      "OCEAN CAPELLA|21530|BULK CARRIER",
      "코리아비너스|29543|TANKER",
      "HOEGH SEOUL|68871|PCTC",
      "KIAN|22360|BULK CARRIER",
      "GRANDE NAPOLI|44431|PCTC",
      "HORIZON TRADER|25171|BULK CARRIER",
      "ALDEN|12225|TANKER",
      "GREAT PANDA|7100|BULK CARRIER",
      "BASTILLE STREET|28778|CRUDE TANKER",
      "에이원|431|TANKER",
      "SHUN FU DA|42895|BULK CARRIER",
      "RONGHE|50927|BULK CARRIER",
      "MSC INES|107551|CONTAINER SHIP",
      "CMA CGM NIAGARA|95680|CONTAINER SHIP",
      "ORIS|3853|TANKER",
      "GLORILAND|5530|TANKER",
      "이에스 로즈|5589|TANKER",
      "성우제주|6562|BULK CARRIER",
      "HARMONY 1|5809|BULK CARRIER",
      "NEPTUNE LINE|5132|CONTAINER SHIP",
      "MERGANSER|25010|BULK CARRIER",
      "ES FUTURE|9992|BULK CARRIER",
      "그레이스 알파|2676|TANKER",
      "우금호|1974|TANKER",
      "신성호|149|TANKER",
      "SETY|31532|GENERAL CARGO",
      "째즈|22988|TANKER",
      "SHENG YUN 7|4675|BULK CARRIER",
      "엠에스클린|3773|TANKER",
      "VARI TRADER|11773|TANKER",
      "FUJI GALAXY|16448|TANKER",
      "BAR|24288|BULK CARRIER",
      "GASCHEM BELUGA|28580|GAS CARRIER",
      "ASIA ASCEND|62929|CRUDE TANKER",
      "KITHNOS|13794|GAS CARRIER",
      "디엘 다이아몬드호|5598|TANKER",
      "ORCHID SYLT|11640|TANKER",
      "정진|7189|BULK CARRIER",
      "TRANS FUTURE 8|28755|PCTC",
      "HONG RUN 16|29436|BULK CARRIER",
      "GAS POWER|46441|GAS CARRIER",
      "VISIO|102784|CRUISE SHIP",
      "ALLEGRA|24479|BULK CARRIER",
      "HTK LOTUS|16960|BULK CARRIER",
      "MING YU 168|26974|BULK CARRIER",
      "DEANA|23224|BULK CARRIER",
      "KEN REI|19781|BULK CARRIER",
      "JK GUNJANG|13174|BULK CARRIER",
      "KEN VISTA|23857|BULK CARRIER",
      "삼표3|5459|BULK CARRIER",
      "EVA BRIGHT|25171|BULK CARRIER",
      "TS HONOUR|24159|BULK CARRIER",
      "오션스프링|21192|BULK CARRIER",
      "에프씨 아도니스|8277|TANKER",
      "UOG GALINI|29124|TANKER",
      "천왕|299|TANKER",
      "유성|1998|TANKER",
      "동남 에이스|1334|TANKER",
      "동방7호|843|TANKER",
      "KEOYOUNG BLUE 3|1395|TANKER",
      "BUENA ESPERANZA|2999|GAS CARRIER",
      "아르고스 레이|75929|PCTC",
      "CMA CGM HOPE|150783|CONTAINER SHIP",
      "MSC C MONTAINE|149944|CONTAINER SHIP",
      "XIN HAI TONG 810|44163|BULK CARRIER",
      "S SELIM|35832|BULK CARRIER",
      "COSCO SHIPPING LILY|157741|CONTAINER SHIP",
      "싸왓디 타일랜드|17518|CONTAINER SHIP",
      "할라크|3486|TANKER",
      "CELEBRITY MILLENNIUM|91011|CRUISE SHIP",
      "송양1호|1201|TANKER",
      "뉴 하모니|4060|TANKER",
      "UNICORN OL|9933|GENERAL CARGO",
      "루나 하나|1075|TANKER",
      "TATEV|17951|BULK CARRIER",
      "GLORIWIND|4587|TANKER",
      "COOL GIRL|8507|냉동 냉장선",
      "ULTRA KUROSHIO|9911|GENERAL CARGO",
      "우성|1998|TANKER",
      "두라썬|2824|TANKER",
      "경성|1994|TANKER",
      "우춘호|3969|TANKER",
      "SUN VENUS|4543|TANKER",
      "에프씨 글로리아|4972|TANKER",
      "107효동케미|2059|케미칼 운반선",
      "글로리 하나|1530|TANKER",
      "제이앤 루비|4111|TANKER",
      "NAVIGATOR CETO|17208|GAS CARRIER",
      "켐 하나|1433|TANKER",
      "거영블루5|1162|TANKER",
      "AAL DAMMAM|25784|GENERAL CARGO",
      "NURI CHEMIST|2583|TANKER",
      "HUA LONG|5834|GENERAL CARGO",
      "제이에스 온산호|4091|TANKER",
      "STOLT DISTRIBUTOR|2700|TANKER",
      "HANYU EMPIRE|4387|TANKER",
      "FUNENG 1|9987|BULK CARRIER",
      "SSI DIGNITY|44003|BULK CARRIER",
      "17유성호|438|TANKER",
      "디케이 이토니아|9413|BULK CARRIER",
      "제유호|124|CRUDE TANKER",
      "LUCKY KOBE|30001|GENERAL CARGO",
      "ANNA M|31117|GENERAL CARGO",
      "에스티 스텔라|1570|BULK CARRIER",
      "스쿠텀|4594|BULK CARRIER",
      "그린 살바도르|49122|GENERAL CARGO",
      "WECAN|9910|CONTAINER SHIP",
      "HAKATA EXPRESS|4867|CONTAINER SHIP",
      "써니 달리아|7634|CONTAINER SHIP",
      "페가서스 테라|9988|CONTAINER SHIP",
      "써니 클로버|9865|CONTAINER SHIP",
      "PROGRESS|9858|CONTAINER SHIP",
      "스카이 제이드|9988|CONTAINER SHIP",
      "써니 아이비|9528|CONTAINER SHIP",
      "아트란틱 사우스|7170|CONTAINER SHIP",
      "HONOR VOYAGER|6393|CONTAINER SHIP",
      "HONOR BRIGHT|7406|CONTAINER SHIP",
      "SUNNY LAVENDER|9865|CONTAINER SHIP",
      "YEOSU VOYAGER|27828|CONTAINER SHIP",
      "챈나이 보야저|25637|CONTAINER SHIP",
      "PACIFIC BUSAN|7170|CONTAINER SHIP",
      "BELAWAN|17225|CONTAINER SHIP",
      "SAWASDEE SIRIUS|18051|CONTAINER SHIP",
      "KMTC INCHEON|17933|CONTAINER SHIP",
      "보스토치니 보이저|7447|CONTAINER SHIP",
      "ZHONG GU PENG LAI|28433|CONTAINER SHIP",
      "고베 트레이더|9944|CONTAINER SHIP",
      "흥아 샤먼|9998|CONTAINER SHIP",
      "STARSHIP URSA|20920|CONTAINER SHIP",
      "센다이 트레이더|9957|CONTAINER SHIP",
      "토야마 트레이더|9980|CONTAINER SHIP",
      "STARSHIP JUPITER|27997|CONTAINER SHIP",
      "SUNNY LAUREL|9870|CONTAINER SHIP",
      "SUNNY VIOLET|9940|CONTAINER SHIP",
      "KYOWA EAGLE|12740|CONTAINER SHIP",
      "KMTC TAIPEIS|18370|CONTAINER SHIP",
      "CA MANILA|17871|CONTAINER SHIP",
      "CLIPPER WILMA|46746|GAS CARRIER",
      "가연|368|TANKER",
      "SPIL NIKEN|25709|CONTAINER SHIP",
      "요코하마 트레이더|9944|CONTAINER SHIP",
      "HANSUNG INCHEON|5888|CONTAINER SHIP",
      "TOKYO CAR|46800|PCTC",
      "DUKE CHEMIST|2993|TANKER",
      "PANCON VICTORY|9923|CONTAINER SHIP",
      "봉은호|314|TANKER",
      "PROVIDENT|6154|CONTAINER SHIP",
      "제7천양|81|TANKER",
      "스카이 빅토리아|9592|CONTAINER SHIP",
      "창용1호|749|TANKER",
      "13대신호|149|TANKER",
      "우원호|497|TANKER",
      "HONOR GLORY|7401|CONTAINER SHIP",
      "스타보이저|9955|CONTAINER SHIP",
      "팬스타 지니 2|7323|CONTAINER SHIP",
      "다인3호|220|TANKER",
      "카리스 CHARIS|1461|TANKER",
      "루비오션호|954|TANKER",
      "부광9호|1045|TANKER",
      "5우영|498|TANKER",
      "제1한미르호|1941|TANKER",
      "BIG GEORGE|25499|CONTAINER SHIP",
      "ATLANTIC BRIDGE|7532|CONTAINER SHIP",
      "GSL CHLOE|26374|CONTAINER SHIP",
      "KMTC PENANG|28736|CONTAINER SHIP",
      "EVER CONFORM|18658|CONTAINER SHIP",
      "그린오션호|1872|TANKER",
      "ITX EHIME|9996|CONTAINER SHIP",
      "SUNNY LILAC|9940|CONTAINER SHIP",
      "ELENA|6030|GENERAL CARGO",
      "CONTSHIP WAY|9948|CONTAINER SHIP",
      "PROSRICH|7589|CONTAINER SHIP",
      "에스엠 자카르타|16850|CONTAINER SHIP",
      "ACX DIAMOND|29060|CONTAINER SHIP",
      "EASLINE KWANGYANG|18502|CONTAINER SHIP",
      "KMTC SINGAPORE|16659|CONTAINER SHIP",
      "스타 파이오니아|9520|CONTAINER SHIP",
      "21부영호|995|TANKER",
      "SKY FLOWER|9742|CONTAINER SHIP",
      "JIN SHUN HE|24002|CONTAINER SHIP",
      "ORION|5372|GENERAL CARGO",
      "EVGENIA|6037|GENERAL CARGO",
      "흥아영|9599|CONTAINER SHIP",
      "ERASMUS FUTURE|9562|CONTAINER SHIP",
      "스카이 프라이드|27154|CONTAINER SHIP",
      "SEOUL GLOW|18123|CONTAINER SHIP",
      "페가서스 페타|9988|CONTAINER SHIP",
      "HAO HAI JI YUN|18667|CONTAINER SHIP",
      "페가서스 드림|9924|CONTAINER SHIP",
      "ARICA BRIDGE|27094|CONTAINER SHIP",
      "PEARL RIVER BRIDGE|17211|CONTAINER SHIP",
      "APL OCEANIA|18485|CONTAINER SHIP",
      "포스요코하마|8306|CONTAINER SHIP",
      "포스 광저우|9969|CONTAINER SHIP",
      "사왓디 리겔|18072|CONTAINER SHIP",
      "STARSHIP AQUILA|18064|CONTAINER SHIP",
      "ONE CLARA|27051|CONTAINER SHIP",
      "ENDEAVOR TIDE|9937|GENERAL CARGO",
      "MAERSK NORESUND|25805|CONTAINER SHIP",
      "SEA OF LUCK|17167|CONTAINER SHIP",
      "뉴기니아 치프|18723|CONTAINER SHIP",
      "HAI RUN SHENG DA|15039|CONTAINER SHIP",
      "스카이 문|9988|CONTAINER SHIP",
      "양쯔 트레이더|9944|CONTAINER SHIP",
      "동진 엔터프라이즈|9990|CONTAINER SHIP",
      "JI YU|6094|CONTAINER SHIP",
      "삼원골드|790|TANKER",
      "HAINA PATRIOT|4047|TANKER",
      "티앤 루나|2253|TANKER",
      "101효동케미호|2204|TANKER",
      "GRAND WINNER 7|29876|케미칼 운반선",
      "청담|1130|급유선",
      "LADY BME|4946|GAS CARRIER",
      "XINXIWANGMINGYUAN|2589|GENERAL CARGO",
      "VW PEACE|5997|GENERAL CARGO",
      "BBC CITRINE|12838|GENERAL CARGO",
      "SILVER SAILING|7243|GENERAL CARGO",
      "BOW OLYMPUS|34148|케미칼 운반선",
      "KMTC SHIMIZU|27997|CONTAINER SHIP",
      "DE MI|2231|BULK CARRIER",
      "HIBIKI|14054|GENERAL CARGO",
      "나고야 트레이더|9524|CONTAINER SHIP",
      "DAEJOO ARIRANG 2|20212|GENERAL CARGO",
      "승진|1635|TANKER",
      "미래3호|996|PCTC",
      "9민성호|337|TANKER",
      "ATLANTIC PIONEER|7532|CONTAINER SHIP",
      "XINQUNDAO|7808|CONTAINER SHIP",
      "SHAO YUN|5272|CONTAINER SHIP",
      "HE YUAN 1|9030|CONTAINER SHIP",
      "XIN MING ZHOU 20|9653|CONTAINER SHIP",
      "XING PING|5275|CONTAINER SHIP",
      "HONOR PROSPER|9990|CONTAINER SHIP",
      "YA LU JIANG|5250|CONTAINER SHIP",
      "상아호|350|TANKER",
      "CONTRIVIA|9972|CONTAINER SHIP",
      "ZHONG SHENG TUO HAI|15512|CONTAINER SHIP",
      "TS TOKYO|17449|CONTAINER SHIP",
      "XIN HE DA|7808|CONTAINER SHIP",
      "CONSISTENCE|9972|CONTAINER SHIP",
      "포스 싱가포르|17846|CONTAINER SHIP",
      "SITC SHENGDE|18820|CONTAINER SHIP",
      "팬콘 챔피언|18606|CONTAINER SHIP",
      "거제유비아|1996|TANKER",
      "동방에이스호|5566|코일전용선",
      "SM JEJU LNG2|9370|GAS CARRIER",
      "거제 이션|1972|TANKER",
      "로얄삼부|2438|TANKER",
      "HONGLI|9916|GAS CARRIER",
      "거영 스타 5|1530|TANKER",
      "럭키오션호|1119|TANKER",
      "CHANG DA 368|5625|GENERAL CARGO",
      "ZI DING XIANG|2450|TANKER",
      "PACIFIC TIANJIN|7464|CONTAINER SHIP",
      "36한진호|299|TANKER",
      "7대복|1996|TANKER",
      "3명광호|299|TANKER",
      "제1거양|104|TANKER",
      "21동방호|373|TANKER",
      "EVER CROWN|18658|CONTAINER SHIP",
      "아람|759|TANKER",
      "11송원호|534|TANKER",
      "흥아 아키타|9998|CONTAINER SHIP",
      "REN JIAN 25|42112|CONTAINER SHIP",
      "써니팜호|3994|CONTAINER SHIP",
      "SUNNY ORCHID|9940|CONTAINER SHIP",
      "우진1호|199|TANKER",
      "거영 블루 7|1119|TANKER",
      "VLADIMIR BIRYUKOV|8318|원양 어선",
      "동방3호|299|TANKER",
      "7보광호|323|TANKER",
      "68세한호|299|TANKER",
      "트리톤|2041|TANKER",
      "KAIROS|29211|TANKER",
      "BLUE KINGDOM|1984|TANKER",
      "MC HERA|30089|케미칼 운반선",
      "PRINCESS IRIS|2652|TANKER",
      "MING PING|1491|BULK CARRIER",
      "백경호|308|TANKER",
      "한유파이오니아|1848|TANKER",
      "ZENITH GLORY|2223|GENERAL CARGO",
      "한성9호|164|TANKER",
      "BLUE WHALE|8973|GAS CARRIER",
      "일신그린아이리스|31005|GENERAL CARGO",
      "TS INDEX|24124|BULK CARRIER",
      "IRIS CORAL|3433|GAS CARRIER",
      "CORAL ACROPORA|6288|GAS CARRIER",
      "SUN DAHLIA|3595|TANKER",
      "라이징 삼부|2691|TANKER",
      "308 HYODONG CHEMI|2682|TANKER",
      "에스티 프레야|2879|GENERAL CARGO",
      "PACIFIC MONACO|7532|CONTAINER SHIP",
      "에스제이아너호|1545|GENERAL CARGO",
      "TIGER CHENNAI|34749|CONTAINER SHIP",
      "ESL KABIR|59307|CONTAINER SHIP",
      "ESL ASANTE|42690|CONTAINER SHIP",
      "ZHONG WAI YUN SHEN ZHEN|9607|CONTAINER SHIP",
      "NEW DRAGON|3675|GENERAL CARGO",
      "MATAKANA ISLAND|19789|GENERAL CARGO",
      "포스 람차방|17846|CONTAINER SHIP",
      "MCC SHENZHEN|17769|CONTAINER SHIP",
      "WOOHYUN HOPE|11481|GENERAL CARGO",
      "JI YONG|8273|CONTAINER SHIP",
      "우리 하나|1066|TANKER",
      "EVER CALM|18658|CONTAINER SHIP",
      "제8에스제이가스|2677|GAS CARRIER",
      "MU DAN YUAN|4830|GAS CARRIER",
      "가스브로드웨이|992|GAS CARRIER",
      "YU CHANG 128|5839|GENERAL CARGO",
      "홍진호|164|TANKER",
      "CORAL ACTINIA|6288|GAS CARRIER",
      "SPRING MOTA|9582|GENERAL CARGO",
      "서해제일1호|97|기타 예선",
      "HAPPY LEADER|17968|BULK CARRIER",
      "한유누리|749|케미칼 운반선",
      "MERATUS JAYAGIRI|25535|CONTAINER SHIP",
      "BRIGHT MOON|4898|GENERAL CARGO",
      "VAST OCEAN|4924|GAS CARRIER",
      "다온|819|TANKER",
      "YONG SHENG 158|8909|GENERAL CARGO",
      "NDL SIX|2369|BULK CARRIER",
      "자카르타 보이저|27061|CONTAINER SHIP",
      "KMTC QINGDAO|27799|CONTAINER SHIP",
      "SITC JUNDE|18819|CONTAINER SHIP",
      "스카이 티아라|9940|CONTAINER SHIP",
      "티와이 인천|7726|CONTAINER SHIP",
      "오성3호|2690|GENERAL CARGO",
      "VALIANT|8270|케미칼 운반선",
      "YUN HAI MIN SHENG|5627|GENERAL CARGO",
      "RONNIE|11494|GENERAL CARGO",
      "포세이돈|2658|GENERAL CARGO",
      "제니스 그레이스|2070|GENERAL CARGO",
      "XIN TAI PING|5275|CONTAINER SHIP",
      "GUANG TONG 15|8720|GENERAL CARGO",
      "TIAN EN 2|8702|GENERAL CARGO",
      "3영호|78|급유선",
      "HUA YUN 1|13647|BULK CARRIER",
      "GAIN SPRING|5211|GENERAL CARGO",
      "KAIROS TRIUMPH|12974|GENERAL CARGO",
      "HYUNDAI MASAN|23265|GENERAL CARGO",
      "AYANA SMILE|13263|GENERAL CARGO",
      "ZENITH OCEAN|2450|GENERAL CARGO",
      "PETROLIMEX 09|25413|케미칼 운반선",
      "뉴 챌린지호|4060|케미칼 운반선",
      "에이치와이 광양|499|TANKER",
      "NING FENG LENG 16|13079|냉동 냉장선",
      "DONGJIN GENIUS|4346|GENERAL CARGO",
      "두라7|6402|TANKER",
      "이스턴 비너스|26594|CRUISE SHIP",
      "대진8001|302|압항 예선",
      "HANSUNG WEIHAI|4867|CONTAINER SHIP",
      "팬콘 선샤인|9923|CONTAINER SHIP",
      "홍콩 보이저|12545|CONTAINER SHIP",
      "스타 익스플로러|9949|CONTAINER SHIP",
      "SONG YUN HE|16737|CONTAINER SHIP",
      "MOJI EXPRESS|4867|CONTAINER SHIP",
      "재원 니케|2701|GENERAL CARGO",
      "REN HE|1499|GENERAL CARGO",
      "에스제이글로리호|1545|GENERAL CARGO",
      "ROTTERDAM TRADER|9755|CONTAINER SHIP",
      "PACIFIC NINGBO|7545|CONTAINER SHIP",
      "HF WEALTH|9610|CONTAINER SHIP",
      "PROSPER|1483|GENERAL CARGO",
      "대성5호|45|견인용예선",
      "아사카|1130|GENERAL CARGO",
      "SUNNY CAMELLIA|9563|CONTAINER SHIP",
      "JIA LONG|2998|GENERAL CARGO",
      "제301삼영호|454|원양 어선",
      "GENERAL TROSHEV|4407|원양 어선",
      "ZALIV ZABIYAKA|4986|원양 어선",
      "대성102호|78|견인용예선",
      "ALIOT|3707|원양 어선",
      "해누리|3408|NON COMMERCIAL SMALL CRAFT",
      "티엔에스 캐쳐|286|견인용예선",
      "WOOYANG LEADER|4825|GENERAL CARGO",
      "ISLAND SKY|4200|CRUISE SHIP",
      "RUI YANG 7|2996|GENERAL CARGO",
      "해원호|320|급유선",
      "뉴 그랜드 피스|33165|국제카페리",
      "동방루비|2879|GENERAL CARGO",
      "SUNNY KALMIA|9940|CONTAINER SHIP",
      "A ROKKO|9562|CONTAINER SHIP",
      "모닝 빅토리호|5222|시멘트운반선",
      "HAFNIA YARRA|43072|케미칼 운반선",
      "에스에스 루나|1520|GENERAL CARGO",
      "퓨쳐 아시아 1|3415|시멘트운반선",
      "WOOYANG GLORY|1681|GENERAL CARGO",
      "ZENITH VICTORY|4898|GENERAL CARGO",
      "오션가스호|3559|GAS CARRIER",
      "아시아가스호|3478|GAS CARRIER",
      "THANG LONG GAS|3434|GAS CARRIER",
      "MARI INNOVATOR|30873|케미칼 운반선",
      "DREAM|77499|CRUISE SHIP",
      "MAGNA|5403|CONTAINER SHIP",
      "스타챌린저|9955|CONTAINER SHIP",
      "INTERASIA TACTIC|30676|CONTAINER SHIP",
      "VICTORIA|34619|BULK CARRIER",
      "ALAMOSBORG|11885|GENERAL CARGO",
      "SCS STAR|2815|GENERAL CARGO",
      "브리지워터 디스커버리|2996|기타선",
      "ANGEL BLUE|1637|TANKER",
      "지 위즈덤|788|GAS CARRIER",
      "ZUIHO MARU|1356|GAS CARRIER",
      "씨가스|3231|GAS CARRIER",
      "BUENA LUNA|4304|GAS CARRIER",
      "CRANE VEGA|3591|GAS CARRIER",
      "XIN HAI 131|5538|BULK CARRIER",
      "ESMERALDA|4484|GAS CARRIER",
      "HAFNIA AQUAMARINE|23676|케미칼 운반선",
      "TORERO|5518|TANKER",
      "마린가스|3241|GAS CARRIER",
      "우동|8581|케미칼 운반선",
      "TONG XIN YUAN|3790|GAS CARRIER",
      "BUENA SUERTE|2997|GAS CARRIER",
      "GAS FRONTIER|4552|GAS CARRIER",
      "레이디가스|3240|GAS CARRIER",
      "GAS ELEGANCE|3591|GAS CARRIER",
      "금향호|223|TANKER",
      "노바|388|PASSENGER SHIP",
      "화정에이스|299|급유선",
      "레이크 오로라|3910|냉동 냉장선",
      "HONG TAI 216|9992|BULK CARRIER",
      "HE HUI 12|5660|GENERAL CARGO",
      "싸왓디 선라이즈|18051|CONTAINER SHIP",
      "동진 엔듀런스|4559|GENERAL CARGO",
      "XIN XIANG LI 56|9337|냉동 냉장선",
      "CRANE URANUS|7910|케미칼 운반선",
      "CRANE REGULUS|4376|케미칼 운반선",
      "드래곤스카이|4738|BULK CARRIER",
      "코롤1호|332|GENERAL CARGO",
      "미라클 알파|2210|케미칼 운반선",
      "SUN SIRIUS|5758|케미칼 운반선",
      "TORVANGER|29712|케미칼 운반선",
      "와이엔 광양|5002|케미칼 운반선",
      "씨에스 오션|5273|케미칼 운반선",
      "SILVER LEO|5760|케미칼 운반선",
      "NING HUA 432|9085|케미칼 운반선",
      "GLOBAL FLORA|7494|케미칼 운반선",
      "TAKAROA SUN|29987|케미칼 운반선",
      "XIN HAI 799|2998|GENERAL CARGO",
      "JIN DONG 9|2396|GENERAL CARGO",
      "리치 세일링|1495|GENERAL CARGO",
      "케이에스 썬글로리|1571|GENERAL CARGO",
      "미래9호|4657|GENERAL CARGO",
      "스카이 호프|9742|CONTAINER SHIP",
      "삼표 1|7123|시멘트운반선",
      "신정601호|127|견인용예선",
      "RISUN 16|1499|GENERAL CARGO",
      "제니스 퀸|4497|GENERAL CARGO",
      "SHANG HUA|1733|GENERAL CARGO",
      "티와이 글로리아호|4105|GENERAL CARGO",
      "JIN YANG|2661|GENERAL CARGO",
      "에스티 벨라|2049|GENERAL CARGO",
      "BS DAESAN|8581|케미칼 운반선",
      "GRAND MUSE|1514|GENERAL CARGO",
      "ADDISON|27779|CONTAINER SHIP",
      "YUAN XIANG FEN JIN|15523|CONTAINER SHIP",
      "HONOR OCEAN|6393|CONTAINER SHIP",
      "에스제이 엔젤|1545|GENERAL CARGO",
      "MING HONG|1431|GENERAL CARGO",
      "JIANG YUAN YUAN DA|9590|CONTAINER SHIP",
      "HENG HE|1496|GENERAL CARGO",
      "DK IMAN|4562|GENERAL CARGO",
      "광양 썬샤인호|2709|GENERAL CARGO",
      "에이치와이 부산|499|TANKER",
      "거영스타3|1826|케미칼 운반선",
      "ZENITH ACE|2450|GENERAL CARGO",
      "1명광호|238|TANKER",
      "8001|3091|경찰정",
      "HONG YANG|1972|GENERAL CARGO",
      "JINHUA 15|1758|GENERAL CARGO",
      "YU DE|4378|GENERAL CARGO",
      "TAURUS|4562|GENERAL CARGO",
      "디케이 아이웨이|1617|GENERAL CARGO",
      "TONG CHENG 198|2999|GENERAL CARGO",
      "DYNAWAY PIONEER|2995|GENERAL CARGO",
      "LIAN YUN 9|2988|GENERAL CARGO",
      "선진호|369|TANKER",
      "XIN HAI 79|4278|GENERAL CARGO",
      "웨스트 카페리|840|GENERAL CARGO",
      "TS MELBOURNE|29658|CONTAINER SHIP",
      "백령 153호|368|GENERAL CARGO",
      "XIN HAI 59|2995|GENERAL CARGO",
      "HIROTO|1998|GENERAL CARGO",
      "HAO XIN|1498|GENERAL CARGO",
      "JIN HUA|2661|GENERAL CARGO",
      "ZENITH GREEN|4898|GENERAL CARGO",
      "GLOBAL STAR|4109|GENERAL CARGO",
      "YING XIN|1499|GENERAL CARGO",
      "HALLA FRONTIER|4881|시멘트운반선",
      "티와이해피|2252|GENERAL CARGO",
      "XI YUN|1482|GENERAL CARGO",
      "SHORYU 3|1499|GENERAL CARGO",
      "MING XI|1496|GENERAL CARGO",
      "PU REN|1482|GENERAL CARGO",
      "비엔알2000호|171|기타 예선",
      "PANSTAR MIRACLE|22129|국제카페리",
      "지민101|143|기타 예선",
      "파라미타|6270|케미칼 운반선",
      "아키타 트레이더|9980|CONTAINER SHIP",
      "써니 아카시아|9867|CONTAINER SHIP",
      "AS PATRIA|27100|CONTAINER SHIP",
      "단양|5996|시멘트운반선",
      "두라 5|3599|TANKER",
      "오션 프라이드 원|6542|PCTC",
      "JI PENG|3994|CONTAINER SHIP",
      "인트란스 에디|7699|케미칼 운반선",
      "BOW EXCELLENCE|29627|케미칼 운반선",
      "썬 에델바이스|3595|케미칼 운반선",
      "SUSANOO|12223|케미칼 운반선",
      "PRINCESS AMBER|4833|케미칼 운반선",
      "XIN HONG XING 229|6683|GENERAL CARGO",
      "TEN JUPITER|9858|CONTAINER SHIP",
      "강남호|113|GENERAL CARGO",
      "AN DONG 68|3988|CONTAINER SHIP",
      "SM JEJU LNG1|9370|GAS CARRIER",
      "GOLDEN CYGNUS|6961|케미칼 운반선",
      "제2승한호|123|TANKER",
      "KMTC PUSAN|16717|CONTAINER SHIP",
      "제6대성호|80|견인용예선",
      "두라스카이|1999|TANKER",
      "팬스타 지니|7323|CONTAINER SHIP",
      "드레넥|225|수상레저기구",
      "WELLINGTON STAR|7944|냉동 냉장선",
      "PONGA|13295|냉동 냉장선",
      "CRYSTAL AFRICA|7057|냉동 냉장선",
      "AZALEA|5997|시멘트운반선",
      "대성201호|143|견인용예선",
      "보넨자|3690|케미칼 운반선",
      "우승호|298|TANKER",
      "골든 오스트라리스|8060|케미칼 운반선",
      "GUANG TONG 33|8537|GENERAL CARGO",
      "제니스 부산|4713|GENERAL CARGO",
      "PACIFIC SINGAPORE|7464|CONTAINER SHIP",
      "FORTUNE 8|1998|BULK CARRIER",
      "YUAN ZHENG|1845|GENERAL CARGO",
      "BS NGHI SON|8593|케미칼 운반선",
      "포천 카렌|7699|케미칼 운반선",
      "대성202호|92|견인용예선",
      "일신프린세스 로얄|5591|철강재 운반선",
      "대한1호|6199|시멘트운반선",
      "광양 프론티어|9751|GENERAL CARGO",
      "티와이 메리|2271|철강재 운반선",
      "코리아 케미|8270|케미칼 운반선",
      "ARDMORE SEAWOLF|29760|케미칼 운반선",
      "자이언트 삼부|5598|케미칼 운반선",
      "본아미|1862|원양 어선",
      "한반도|5255|NON COMMERCIAL SMALL CRAFT",
      "아약스|714|원양 어선",
      "EASTERN TRITON|3491|케미칼 운반선",
      "거영스타호|1530|케미칼 운반선",
      "안성201호|143|기타 예선",
      "우찬|8539|케미칼 운반선",
      "케이티에스 실버|2193|케미칼 운반선",
      "썬퀸|2993|케미칼 운반선",
      "GOLDEN GLORY|4040|케미칼 운반선",
      "CRANE MAIA|4873|케미칼 운반선",
      "티와이 에버호|4105|BULK CARRIER",
      "성진3호|316|기타 예선",
      "서해15호|198|기타 예선",
      "103 성신호|216|기타 예선",
      "강남티 9호|87|견인용예선",
      "뉴 카멜리아|19961|PASSENGER SHIP",
      "제11쌍용|1117|BULK CARRIER",
      "한미르|1520|NON COMMERCIAL SMALL CRAFT",
      "MIR HANA|1445|케미칼 운반선",
      "RONG KAI|1499|GENERAL CARGO",
      "XIN FENG HAI|2915|GENERAL CARGO",
      "RUN KAI|1499|GENERAL CARGO",
      "아라온 ARAON|7507|NON COMMERCIAL SMALL CRAFT",
      "한나래호|6280|NON COMMERCIAL SMALL CRAFT",
      "BRIGHT SUN|4898|GENERAL CARGO",
      "금양3호|141|TANKER",
      "BASAR|4415|원양 어선",
      "YEONSUNG|303|견인용예선",
      "수성7|4810|시멘트운반선",
      "은호|35|견인용예선",
      "골든 조이 하나호|2498|케미칼 운반선",
      "그레이스삼부|1755|케미칼 운반선",
      "202고려호|72|견인용예선",
      "625 덕양|226|기타선",
      "대진8006|411|압항 예선",
      "108대양호|277|압항 예선",
      "901조양|232|기타 예선",
      "EGS SURVEYOR II|1081|기타선",
      "수성5|4803|시멘트운반선",
      "젬 라토야|42697|케미칼 운반선",
      "아그네스90|414|원양 어선",
      "연성88호|105|기타선",
      "207동성호|87|견인용예선",
      "103 효동케미|2367|케미칼 운반선",
      "20청우호|299|급유선",
      "HUI JI|2565|GENERAL CARGO",
      "JINHUA 11|1753|GENERAL CARGO",
      "일성103호|175|이 접안용 예선",
      "HONG QIAO|1972|GENERAL CARGO",
      "탐사호|94|기타선",
      "선우자이언트호|25|기타선",
      "EURO STAR|4364|냉동 냉장선",
      "101성신호|125|기타 예선",
      "스카이로얄|1716|케미칼 운반선",
      "태림재스민호|465|냉동 냉장선",
      "수성3|4771|시멘트운반선",
      "씨플라워|388|PASSENGER SHIP",
      "팬스타 쓰시마 링크|457|PASSENGER SHIP",
      "넘버투 조초|4546|냉동 냉장선",
      "울산705호|173|견인용예선",
      "NAZIMOV|714|원양 어선",
      "77삼영호|107|견인용예선",
      "노빅|714|원양 어선",
      "ULTIMATE|947|원양 어선",
      "BUKHTA ASACHA|3235|냉동 냉장선",
      "RINA SEA|4660|GENERAL CARGO",
      "BAKLANOVO|4347|원양 어선",
      "해진|4723|시멘트운반선",
      "제101삼일호|302|압항 예선",
      "신시지 112|1813|원양 어선",
      "BIKIN|235|원양 어선",
      "KIBENA 1|1837|원양 어선",
      "프레가트|664|원양 어선",
      "블루오션|1108|급유선",
      "골든 그레이스 하나|2997|케미칼 운반선",
      "우진 파이오니어호|2362|케미칼 운반선",
      "GRACE SULPHUR|2304|케미칼 운반선",
      "필로스 1|1500|케미칼 운반선",
      "XUAN JING|1956|케미칼 운반선",
      "ORIENTAL PEARL VIII|24748|국제카페리",
      "유진1호|241|견인용예선",
      "제물포2호|22|견인용예선",
      "이코노스타|24|견인용예선",
      "수경호|149|TANKER",
      "선라이즈 삼부|2403|케미칼 운반선",
      "티와이아이리스호|4105|GENERAL CARGO",
      "JINHUA 9|2994|GENERAL CARGO",
      "12한진호|322|급유선",
      "ALLIANCE NO 2|1490|GENERAL CARGO",
      "NO 102 KUM YANG|544|원양 어선",
      "KAMLAYN|1164|원양 어선",
      "아틀란트|1198|원양 어선",
      "ECOPACIFIC|741|원양 어선",
      "삼양505호|94|견인용예선",
      "15선영호|497|급유선",
      "현대 당진|2792|GENERAL CARGO",
      "신향설란|32729|국제카페리",
      "NEW GOLDEN BRIDGE V|29554|국제카페리",
      "SUN LORD|2389|케미칼 운반선",
      "성희호|8076|국제카페리",
      "FU YUAN YU 8295|1653|원양 어선",
      "FU YUAN YU 8299|1653|원양 어선",
      "FU YUAN YU 8298|1653|원양 어선",
      "7세윤호|299|급유선",
      "강남101호|65|견인용예선",
      "에스앤비1호|149|견인용예선",
      "1003종영호|46|기타 예선",
      "수성2|5963|시멘트운반선",
      "대성101호|124|기타 예선",
      "건룡호|198|급유선",
      "유쇼 마루|834|케미칼 운반선",
      "오션에이스 2호|299|급유선",
      "메가 파이오니아호|3543|GENERAL CARGO",
      "한진3007호|3810|핫코일운반선",
      "명진호|460|급유선",
      "광양12호|2440|철강재 운반선",
      "근양|5996|시멘트운반선",
      "대성7호|91|견인용예선",
      "105성신호|140|견인용예선",
      "SD GLORIA|4064|시멘트운반선",
      "강남T 13호|83|견인용예선",
      "AKIMOTO|4333|GENERAL CARGO",
      "해신102|180|견인용예선",
      "금오티1호|213|기타 예선",
      "부강1|257|기타 예선",
      "광진월드3호|176|견인용예선",
      "광성호|336|급유선",
      "32대영호|200|급유선",
      "302종영호|79|견인용예선",
      "유진|4727|시멘트운반선",
      "101신동|94|기타선",
      "202대양호|355|압항 예선",
      "덕양5001호|770|일반화물운반용 부선",
      "대성8001|2052|기타 부선"
    ]
  },
  "source_layer": "auxiliary",
  "load_strategy": "lazy",
  "startup_safe": false,
  "core_blocking": false,
  "owner_tier": "reference_enrichment",
  "core_may_update": false,
  "enrichment_run_id": "run_20260613033359476_4972d654",
  "active_core_run_id_used_for_matching": "run_20260612215215093_9a4e8bcc",
  "source_run_ids": {
    "source_csv": "run_20260612160015353_e7b1a2b2",
    "vessel_spec": "run_20260612160015353_e7b1a2b2",
    "pilot_sources": "run_20260612160015353_e7b1a2b2",
    "berth_sources": "run_20260612160015353_e7b1a2b2",
    "mof_ais_dynamic": "run_20260612160015353_e7b1a2b2",
    "mof_ais_info": "run_20260612160015353_e7b1a2b2",
    "mof_ais_stat": "run_20260612160015353_e7b1a2b2",
    "ulsan_core": "run_20260612160015353_e7b1a2b2",
    "ulsan_berth_detail": "run_20260612160015353_e7b1a2b2",
    "ulsan_cargo_plan": "run_20260612160015353_e7b1a2b2",
    "ulsan_berth_operation": "run_20260612160015353_e7b1a2b2",
    "ulsan_terminal_process": "run_20260612160015353_e7b1a2b2",
    "port_operation": "run_20260612160015353_e7b1a2b2"
  },
  "status_run_id": "run_20260613033359476_4972d654",
  "stale_diagnostic": false,
  "stale_reason": "",
  "placeholder": false
}
