{
  "schema_version": "1.0",
  "generated_at": "2026-06-12T08:35:08.970Z",
  "data_mode": "live",
  "run_id": "run_20260612082743789_e376b650",
  "source_run_id": "run_20260612082743789_e376b650",
  "snapshot_context": {
    "run_id": "run_20260612082743789_e376b650",
    "generated_at": "2026-06-12T08:35:08.970Z",
    "data_mode": "live",
    "source_run_id": "run_20260612082743789_e376b650"
  },
  "record_count": 39,
  "item_count": 39,
  "endpoints": [
    {
      "key": "bootstrap",
      "path": "dashboard/api/bootstrap.json",
      "exists": true,
      "first_char": "{",
      "root_type": "object",
      "parsed_from_disk": true,
      "parse_checked_at": "2026-06-12T08:35:08.970Z",
      "valid_json": true,
      "schema_valid": true,
      "record_count": 33,
      "item_count": 9,
      "size_kb": 118.7,
      "bytes": 121529,
      "source_layer": "core",
      "startup_safe": true,
      "load_strategy": "initial",
      "duplicated_payload_risk": "LOW",
      "summary_available": false,
      "detail_available": false,
      "recommended_load": "initial",
      "max_recommended_size_kb": 150,
      "status": "OK",
      "problem": ""
    },
    {
      "key": "status.summary",
      "path": "dashboard/api/status-summary.json",
      "exists": true,
      "first_char": "{",
      "root_type": "object",
      "parsed_from_disk": true,
      "parse_checked_at": "2026-06-12T08:35:08.970Z",
      "valid_json": true,
      "schema_valid": true,
      "record_count": 33,
      "item_count": 0,
      "size_kb": 3.1,
      "bytes": 3124,
      "source_layer": "core",
      "startup_safe": true,
      "load_strategy": "initial",
      "duplicated_payload_risk": "LOW",
      "summary_available": true,
      "detail_available": true,
      "recommended_load": "initial",
      "max_recommended_size_kb": 100,
      "status": "OK",
      "problem": ""
    },
    {
      "key": "vessel.countReconciliation",
      "path": "dashboard/api/vessel-count-reconciliation.json",
      "exists": true,
      "first_char": "{",
      "root_type": "object",
      "parsed_from_disk": true,
      "parse_checked_at": "2026-06-12T08:35:08.970Z",
      "valid_json": true,
      "schema_valid": true,
      "record_count": 1043,
      "item_count": 0,
      "size_kb": 6.4,
      "bytes": 6505,
      "source_layer": "core",
      "startup_safe": true,
      "load_strategy": "initial",
      "duplicated_payload_risk": "LOW",
      "summary_available": false,
      "detail_available": false,
      "recommended_load": "initial",
      "max_recommended_size_kb": 100,
      "status": "OK",
      "problem": ""
    },
    {
      "key": "vessels.index",
      "path": "dashboard/api/vessels/index.json",
      "exists": true,
      "first_char": "{",
      "root_type": "object",
      "parsed_from_disk": true,
      "parse_checked_at": "2026-06-12T08:35:08.970Z",
      "valid_json": true,
      "schema_valid": true,
      "record_count": 692,
      "item_count": 0,
      "size_kb": 1.2,
      "bytes": 1256,
      "source_layer": "core",
      "startup_safe": true,
      "load_strategy": "initial",
      "duplicated_payload_risk": "LOW",
      "summary_available": false,
      "detail_available": false,
      "recommended_load": "initial",
      "max_recommended_size_kb": 100,
      "status": "OK",
      "problem": ""
    },
    {
      "key": "ports",
      "path": "dashboard/api/ports.json",
      "exists": true,
      "first_char": "{",
      "root_type": "object",
      "parsed_from_disk": true,
      "parse_checked_at": "2026-06-12T08:35:08.970Z",
      "valid_json": true,
      "schema_valid": true,
      "record_count": 9,
      "item_count": 9,
      "size_kb": 9.4,
      "bytes": 9629,
      "source_layer": "core",
      "startup_safe": true,
      "load_strategy": "initial",
      "duplicated_payload_risk": "LOW",
      "summary_available": false,
      "detail_available": false,
      "recommended_load": "initial",
      "max_recommended_size_kb": 100,
      "status": "OK",
      "problem": ""
    },
    {
      "key": "candidates.topSummary",
      "path": "dashboard/api/candidates/top-summary.json",
      "exists": true,
      "first_char": "{",
      "root_type": "object",
      "parsed_from_disk": true,
      "parse_checked_at": "2026-06-12T08:35:08.970Z",
      "valid_json": true,
      "schema_valid": true,
      "record_count": 50,
      "item_count": 5,
      "size_kb": 7.5,
      "bytes": 7656,
      "source_layer": "core",
      "startup_safe": false,
      "load_strategy": "lazy",
      "duplicated_payload_risk": "LOW",
      "summary_available": true,
      "detail_available": true,
      "recommended_load": "summary",
      "max_recommended_size_kb": 100,
      "status": "OK",
      "problem": ""
    },
    {
      "key": "candidates.top",
      "path": "dashboard/api/candidates/top.json",
      "exists": true,
      "first_char": "{",
      "root_type": "object",
      "parsed_from_disk": true,
      "parse_checked_at": "2026-06-12T08:35:08.970Z",
      "valid_json": true,
      "schema_valid": true,
      "record_count": 50,
      "item_count": 50,
      "size_kb": 1852.9,
      "bytes": 1897347,
      "source_layer": "core",
      "startup_safe": false,
      "load_strategy": "lazy",
      "duplicated_payload_risk": "HIGH",
      "summary_available": true,
      "detail_available": true,
      "recommended_load": "lazy_detail",
      "max_recommended_size_kb": 500,
      "status": "TOO_LARGE",
      "problem": "1853KB; summary/detail split recommended"
    },
    {
      "key": "status",
      "path": "dashboard/api/status.json",
      "exists": true,
      "first_char": "{",
      "root_type": "object",
      "parsed_from_disk": true,
      "parse_checked_at": "2026-06-12T08:35:08.970Z",
      "valid_json": true,
      "schema_valid": true,
      "record_count": 33,
      "item_count": 9,
      "size_kb": 1701.1,
      "bytes": 1741917,
      "source_layer": "diagnostic",
      "startup_safe": false,
      "load_strategy": "diagnostic_only",
      "duplicated_payload_risk": "HIGH",
      "summary_available": true,
      "detail_available": true,
      "recommended_load": "lazy_detail",
      "max_recommended_size_kb": 500,
      "status": "TOO_LARGE",
      "problem": "1701KB; summary/detail split recommended"
    },
    {
      "key": "dashboard-summary",
      "path": "dashboard/api/dashboard-summary.json",
      "exists": true,
      "first_char": "{",
      "root_type": "object",
      "parsed_from_disk": true,
      "parse_checked_at": "2026-06-12T08:35:08.970Z",
      "valid_json": true,
      "schema_valid": true,
      "record_count": 33,
      "item_count": 9,
      "size_kb": 402.6,
      "bytes": 412254,
      "source_layer": "core",
      "startup_safe": false,
      "load_strategy": "lazy",
      "duplicated_payload_risk": "LOW",
      "summary_available": false,
      "detail_available": false,
      "recommended_load": "lazy",
      "max_recommended_size_kb": 500,
      "status": "OK",
      "problem": ""
    },
    {
      "key": "sales.actionsSummary",
      "path": "dashboard/api/sales/actions-summary.json",
      "exists": true,
      "first_char": "{",
      "root_type": "object",
      "parsed_from_disk": true,
      "parse_checked_at": "2026-06-12T08:35:08.970Z",
      "valid_json": true,
      "schema_valid": true,
      "record_count": 63,
      "item_count": 5,
      "size_kb": 7,
      "bytes": 7214,
      "source_layer": "core",
      "startup_safe": false,
      "load_strategy": "lazy",
      "duplicated_payload_risk": "LOW",
      "summary_available": true,
      "detail_available": true,
      "recommended_load": "summary",
      "max_recommended_size_kb": 100,
      "status": "OK",
      "problem": ""
    },
    {
      "key": "sales.actions",
      "path": "dashboard/api/sales/actions.json",
      "exists": true,
      "first_char": "{",
      "root_type": "object",
      "parsed_from_disk": true,
      "parse_checked_at": "2026-06-12T08:35:08.970Z",
      "valid_json": true,
      "schema_valid": true,
      "record_count": 63,
      "item_count": 63,
      "size_kb": 613.6,
      "bytes": 628322,
      "source_layer": "core",
      "startup_safe": false,
      "load_strategy": "lazy",
      "duplicated_payload_risk": "HIGH",
      "summary_available": true,
      "detail_available": true,
      "recommended_load": "lazy_detail",
      "max_recommended_size_kb": 500,
      "status": "TOO_LARGE",
      "problem": "614KB; summary/detail split recommended"
    },
    {
      "key": "sales.conversionPipeline",
      "path": "dashboard/api/sales/conversion-pipeline.json",
      "exists": true,
      "first_char": "{",
      "root_type": "object",
      "parsed_from_disk": true,
      "parse_checked_at": "2026-06-12T08:35:08.970Z",
      "valid_json": true,
      "schema_valid": true,
      "record_count": 33,
      "item_count": 33,
      "size_kb": 297.9,
      "bytes": 305059,
      "source_layer": "core",
      "startup_safe": false,
      "load_strategy": "lazy",
      "duplicated_payload_risk": "MEDIUM",
      "summary_available": false,
      "detail_available": false,
      "recommended_load": "lazy",
      "max_recommended_size_kb": 500,
      "status": "OK",
      "problem": ""
    },
    {
      "key": "sales.quoteOpportunities",
      "path": "dashboard/api/sales/quote-opportunities.json",
      "exists": true,
      "first_char": "{",
      "root_type": "object",
      "parsed_from_disk": true,
      "parse_checked_at": "2026-06-12T08:35:08.970Z",
      "valid_json": true,
      "schema_valid": true,
      "record_count": 36,
      "item_count": 36,
      "size_kb": 405.1,
      "bytes": 414792,
      "source_layer": "core",
      "startup_safe": false,
      "load_strategy": "lazy",
      "duplicated_payload_risk": "MEDIUM",
      "summary_available": false,
      "detail_available": false,
      "recommended_load": "lazy",
      "max_recommended_size_kb": 500,
      "status": "OK",
      "problem": ""
    },
    {
      "key": "sales.verificationQueueSummary",
      "path": "dashboard/api/sales/verification-queue-summary.json",
      "exists": true,
      "first_char": "{",
      "root_type": "object",
      "parsed_from_disk": true,
      "parse_checked_at": "2026-06-12T08:35:08.970Z",
      "valid_json": true,
      "schema_valid": true,
      "record_count": 99,
      "item_count": 5,
      "size_kb": 6.9,
      "bytes": 7094,
      "source_layer": "core",
      "startup_safe": true,
      "load_strategy": "initial",
      "duplicated_payload_risk": "LOW",
      "summary_available": true,
      "detail_available": true,
      "recommended_load": "initial",
      "max_recommended_size_kb": 100,
      "status": "OK",
      "problem": ""
    },
    {
      "key": "sales.verificationQueue",
      "path": "dashboard/api/sales/verification-queue.json",
      "exists": true,
      "first_char": "{",
      "root_type": "object",
      "parsed_from_disk": true,
      "parse_checked_at": "2026-06-12T08:35:08.970Z",
      "valid_json": true,
      "schema_valid": true,
      "record_count": 99,
      "item_count": 99,
      "size_kb": 810.7,
      "bytes": 830138,
      "source_layer": "core",
      "startup_safe": false,
      "load_strategy": "lazy",
      "duplicated_payload_risk": "HIGH",
      "summary_available": true,
      "detail_available": true,
      "recommended_load": "lazy_detail",
      "max_recommended_size_kb": 500,
      "status": "TOO_LARGE",
      "problem": "811KB; summary/detail split recommended"
    },
    {
      "key": "watchlist.current",
      "path": "dashboard/api/watchlist/current.json",
      "exists": true,
      "first_char": "{",
      "root_type": "object",
      "parsed_from_disk": true,
      "parse_checked_at": "2026-06-12T08:35:08.970Z",
      "valid_json": true,
      "schema_valid": true,
      "record_count": 20,
      "item_count": 20,
      "size_kb": 160.1,
      "bytes": 163899,
      "source_layer": "core",
      "startup_safe": false,
      "load_strategy": "lazy",
      "duplicated_payload_risk": "LOW",
      "summary_available": false,
      "detail_available": false,
      "recommended_load": "lazy",
      "max_recommended_size_kb": 500,
      "status": "OK",
      "problem": ""
    },
    {
      "key": "targets.currentSummary",
      "path": "dashboard/api/targets/current-summary.json",
      "exists": true,
      "first_char": "{",
      "root_type": "object",
      "parsed_from_disk": true,
      "parse_checked_at": "2026-06-12T08:35:08.970Z",
      "valid_json": true,
      "schema_valid": true,
      "record_count": 33,
      "item_count": 5,
      "size_kb": 6.9,
      "bytes": 7044,
      "source_layer": "core",
      "startup_safe": false,
      "load_strategy": "lazy",
      "duplicated_payload_risk": "LOW",
      "summary_available": true,
      "detail_available": true,
      "recommended_load": "summary",
      "max_recommended_size_kb": 100,
      "status": "OK",
      "problem": ""
    },
    {
      "key": "targets.current",
      "path": "dashboard/api/targets/current.json",
      "exists": true,
      "first_char": "{",
      "root_type": "object",
      "parsed_from_disk": true,
      "parse_checked_at": "2026-06-12T08:35:08.970Z",
      "valid_json": true,
      "schema_valid": true,
      "record_count": 33,
      "item_count": 33,
      "size_kb": 668.9,
      "bytes": 684967,
      "source_layer": "core",
      "startup_safe": false,
      "load_strategy": "lazy",
      "duplicated_payload_risk": "HIGH",
      "summary_available": true,
      "detail_available": true,
      "recommended_load": "lazy_detail",
      "max_recommended_size_kb": 500,
      "status": "TOO_LARGE",
      "problem": "669KB; summary/detail split recommended"
    },
    {
      "key": "targets.categoriesSummary",
      "path": "dashboard/api/targets/categories-summary.json",
      "exists": true,
      "first_char": "{",
      "root_type": "object",
      "parsed_from_disk": true,
      "parse_checked_at": "2026-06-12T08:35:08.970Z",
      "valid_json": true,
      "schema_valid": true,
      "record_count": 33,
      "item_count": 10,
      "size_kb": 48.1,
      "bytes": 49261,
      "source_layer": "core",
      "startup_safe": true,
      "load_strategy": "initial",
      "duplicated_payload_risk": "LOW",
      "summary_available": true,
      "detail_available": true,
      "recommended_load": "initial",
      "max_recommended_size_kb": 100,
      "status": "OK",
      "problem": ""
    },
    {
      "key": "targets.categories",
      "path": "dashboard/api/targets/categories.json",
      "exists": true,
      "first_char": "{",
      "root_type": "object",
      "parsed_from_disk": true,
      "parse_checked_at": "2026-06-12T08:35:08.970Z",
      "valid_json": true,
      "schema_valid": true,
      "record_count": 33,
      "item_count": 10,
      "size_kb": 3917.1,
      "bytes": 4011113,
      "source_layer": "core",
      "startup_safe": false,
      "load_strategy": "lazy",
      "duplicated_payload_risk": "HIGH",
      "summary_available": true,
      "detail_available": true,
      "recommended_load": "lazy_detail",
      "max_recommended_size_kb": 500,
      "status": "TOO_LARGE",
      "problem": "3917KB; summary/detail split recommended"
    },
    {
      "key": "vessels.page1",
      "path": "dashboard/api/vessels/page-1.json",
      "exists": true,
      "first_char": "{",
      "root_type": "object",
      "parsed_from_disk": true,
      "parse_checked_at": "2026-06-12T08:35:08.970Z",
      "valid_json": true,
      "schema_valid": true,
      "record_count": 692,
      "item_count": 30,
      "size_kb": 259.3,
      "bytes": 265550,
      "source_layer": "core",
      "startup_safe": false,
      "load_strategy": "lazy",
      "duplicated_payload_risk": "MEDIUM",
      "summary_available": false,
      "detail_available": false,
      "recommended_load": "lazy",
      "max_recommended_size_kb": 500,
      "status": "OK",
      "problem": ""
    },
    {
      "key": "aux.sourceCsvSummary",
      "path": "dashboard/api/aux/source-csv-summary.json",
      "exists": true,
      "first_char": "{",
      "root_type": "object",
      "parsed_from_disk": true,
      "parse_checked_at": "2026-06-12T08:35:08.970Z",
      "valid_json": true,
      "schema_valid": true,
      "record_count": 0,
      "item_count": 0,
      "size_kb": 1.5,
      "bytes": 1542,
      "source_layer": "auxiliary",
      "startup_safe": false,
      "load_strategy": "lazy",
      "duplicated_payload_risk": "LOW",
      "summary_available": false,
      "detail_available": false,
      "recommended_load": "lazy",
      "max_recommended_size_kb": 500,
      "status": "EMPTY_VALID",
      "problem": ""
    },
    {
      "key": "aux.pilotageSummary",
      "path": "dashboard/api/aux/pilotage-summary.json",
      "exists": true,
      "first_char": "{",
      "root_type": "object",
      "parsed_from_disk": true,
      "parse_checked_at": "2026-06-12T08:35:08.970Z",
      "valid_json": true,
      "schema_valid": true,
      "record_count": 403,
      "item_count": 0,
      "size_kb": 3,
      "bytes": 3026,
      "source_layer": "auxiliary",
      "startup_safe": false,
      "load_strategy": "lazy",
      "duplicated_payload_risk": "LOW",
      "summary_available": false,
      "detail_available": false,
      "recommended_load": "lazy",
      "max_recommended_size_kb": 500,
      "status": "OK",
      "problem": ""
    },
    {
      "key": "aux.berthSummary",
      "path": "dashboard/api/aux/berth-summary.json",
      "exists": true,
      "first_char": "{",
      "root_type": "object",
      "parsed_from_disk": true,
      "parse_checked_at": "2026-06-12T08:35:08.970Z",
      "valid_json": true,
      "schema_valid": true,
      "record_count": 30,
      "item_count": 0,
      "size_kb": 2.2,
      "bytes": 2279,
      "source_layer": "auxiliary",
      "startup_safe": false,
      "load_strategy": "lazy",
      "duplicated_payload_risk": "LOW",
      "summary_available": false,
      "detail_available": false,
      "recommended_load": "lazy",
      "max_recommended_size_kb": 500,
      "status": "OK",
      "problem": ""
    },
    {
      "key": "aux.aisInfoSummary",
      "path": "dashboard/api/aux/ais-info-summary.json",
      "exists": true,
      "first_char": "{",
      "root_type": "object",
      "parsed_from_disk": true,
      "parse_checked_at": "2026-06-12T08:35:08.970Z",
      "valid_json": true,
      "schema_valid": true,
      "record_count": 10,
      "item_count": 0,
      "size_kb": 2.2,
      "bytes": 2233,
      "source_layer": "auxiliary",
      "startup_safe": false,
      "load_strategy": "lazy",
      "duplicated_payload_risk": "LOW",
      "summary_available": false,
      "detail_available": false,
      "recommended_load": "lazy",
      "max_recommended_size_kb": 500,
      "status": "OK",
      "problem": ""
    },
    {
      "key": "aux.aisDynamicSummary",
      "path": "dashboard/api/aux/ais-dynamic-summary.json",
      "exists": true,
      "first_char": "{",
      "root_type": "object",
      "parsed_from_disk": true,
      "parse_checked_at": "2026-06-12T08:35:08.970Z",
      "valid_json": true,
      "schema_valid": true,
      "record_count": 20,
      "item_count": 0,
      "size_kb": 2.4,
      "bytes": 2441,
      "source_layer": "auxiliary",
      "startup_safe": false,
      "load_strategy": "lazy",
      "duplicated_payload_risk": "LOW",
      "summary_available": false,
      "detail_available": false,
      "recommended_load": "lazy",
      "max_recommended_size_kb": 500,
      "status": "OK",
      "problem": ""
    },
    {
      "key": "aux.vesselSpecSummary",
      "path": "dashboard/api/aux/vessel-spec-summary.json",
      "exists": true,
      "first_char": "{",
      "root_type": "object",
      "parsed_from_disk": true,
      "parse_checked_at": "2026-06-12T08:35:08.970Z",
      "valid_json": true,
      "schema_valid": true,
      "record_count": 1,
      "item_count": 0,
      "size_kb": 2.2,
      "bytes": 2247,
      "source_layer": "auxiliary",
      "startup_safe": false,
      "load_strategy": "lazy",
      "duplicated_payload_risk": "LOW",
      "summary_available": false,
      "detail_available": false,
      "recommended_load": "lazy",
      "max_recommended_size_kb": 500,
      "status": "OK",
      "problem": ""
    },
    {
      "key": "source.healthRuntime",
      "path": "dashboard/api/source-health-runtime.json",
      "exists": true,
      "first_char": "{",
      "root_type": "object",
      "parsed_from_disk": true,
      "parse_checked_at": "2026-06-12T08:35:08.970Z",
      "valid_json": true,
      "schema_valid": true,
      "record_count": 48,
      "item_count": 0,
      "size_kb": 104.7,
      "bytes": 107172,
      "source_layer": "diagnostic",
      "startup_safe": false,
      "load_strategy": "diagnostic_only",
      "duplicated_payload_risk": "LOW",
      "summary_available": false,
      "detail_available": false,
      "recommended_load": "diagnostic_only",
      "max_recommended_size_kb": 500,
      "status": "OK",
      "problem": ""
    },
    {
      "key": "source.collectionStatus",
      "path": "dashboard/api/source-collection-status.json",
      "exists": true,
      "first_char": "{",
      "root_type": "object",
      "parsed_from_disk": true,
      "parse_checked_at": "2026-06-12T08:35:08.970Z",
      "valid_json": true,
      "schema_valid": true,
      "record_count": 13,
      "item_count": 13,
      "size_kb": 81,
      "bytes": 82916,
      "source_layer": "diagnostic",
      "startup_safe": false,
      "load_strategy": "diagnostic_only",
      "duplicated_payload_risk": "LOW",
      "summary_available": false,
      "detail_available": false,
      "recommended_load": "diagnostic_only",
      "max_recommended_size_kb": 500,
      "status": "OK",
      "problem": ""
    },
    {
      "key": "storage.efficiency",
      "path": "dashboard/api/storage-efficiency-report.json",
      "exists": true,
      "first_char": "{",
      "root_type": "object",
      "parsed_from_disk": true,
      "parse_checked_at": "2026-06-12T08:35:08.970Z",
      "valid_json": true,
      "schema_valid": true,
      "record_count": 5,
      "item_count": 0,
      "size_kb": 2.9,
      "bytes": 2974,
      "source_layer": "diagnostic",
      "startup_safe": false,
      "load_strategy": "diagnostic_only",
      "duplicated_payload_risk": "LOW",
      "summary_available": false,
      "detail_available": false,
      "recommended_load": "diagnostic_only",
      "max_recommended_size_kb": 500,
      "status": "OK",
      "problem": ""
    },
    {
      "key": "intelligence.fleetIntelligence",
      "path": "dashboard/api/intelligence/fleet-intelligence.json",
      "exists": true,
      "first_char": "{",
      "root_type": "object",
      "parsed_from_disk": true,
      "parse_checked_at": "2026-06-12T08:35:08.970Z",
      "valid_json": true,
      "schema_valid": true,
      "record_count": 3,
      "item_count": 3,
      "size_kb": 36.3,
      "bytes": 37135,
      "source_layer": "core",
      "startup_safe": false,
      "load_strategy": "lazy",
      "duplicated_payload_risk": "LOW",
      "summary_available": false,
      "detail_available": false,
      "recommended_load": "lazy",
      "max_recommended_size_kb": 500,
      "status": "OK",
      "problem": ""
    },
    {
      "key": "intelligence.fleetPenetration",
      "path": "dashboard/api/intelligence/fleet-penetration.json",
      "exists": true,
      "first_char": "{",
      "root_type": "object",
      "parsed_from_disk": true,
      "parse_checked_at": "2026-06-12T08:35:08.970Z",
      "valid_json": true,
      "schema_valid": true,
      "record_count": 3,
      "item_count": 3,
      "size_kb": 34.5,
      "bytes": 35327,
      "source_layer": "core",
      "startup_safe": false,
      "load_strategy": "lazy",
      "duplicated_payload_risk": "LOW",
      "summary_available": false,
      "detail_available": false,
      "recommended_load": "lazy",
      "max_recommended_size_kb": 500,
      "status": "OK",
      "problem": ""
    },
    {
      "key": "intelligence.revenueForecast",
      "path": "dashboard/api/intelligence/revenue-forecast.json",
      "exists": true,
      "first_char": "{",
      "root_type": "object",
      "parsed_from_disk": true,
      "parse_checked_at": "2026-06-12T08:35:08.970Z",
      "valid_json": true,
      "schema_valid": true,
      "record_count": 1,
      "item_count": 1,
      "size_kb": 25,
      "bytes": 25592,
      "source_layer": "core",
      "startup_safe": false,
      "load_strategy": "lazy",
      "duplicated_payload_risk": "LOW",
      "summary_available": false,
      "detail_available": false,
      "recommended_load": "lazy",
      "max_recommended_size_kb": 500,
      "status": "OK",
      "problem": ""
    },
    {
      "key": "intelligence.portDna",
      "path": "dashboard/api/intelligence/port-dna.json",
      "exists": true,
      "first_char": "{",
      "root_type": "object",
      "parsed_from_disk": true,
      "parse_checked_at": "2026-06-12T08:35:08.970Z",
      "valid_json": true,
      "schema_valid": true,
      "record_count": 10,
      "item_count": 10,
      "size_kb": 67.3,
      "bytes": 68927,
      "source_layer": "core",
      "startup_safe": false,
      "load_strategy": "lazy",
      "duplicated_payload_risk": "LOW",
      "summary_available": false,
      "detail_available": false,
      "recommended_load": "lazy",
      "max_recommended_size_kb": 500,
      "status": "OK",
      "problem": ""
    },
    {
      "key": "intelligence.opportunityMemory",
      "path": "dashboard/api/intelligence/opportunity-memory.json",
      "exists": true,
      "first_char": "{",
      "root_type": "object",
      "parsed_from_disk": true,
      "parse_checked_at": "2026-06-12T08:35:08.970Z",
      "valid_json": true,
      "schema_valid": true,
      "record_count": 10,
      "item_count": 10,
      "size_kb": 174.1,
      "bytes": 178270,
      "source_layer": "core",
      "startup_safe": false,
      "load_strategy": "lazy",
      "duplicated_payload_risk": "MEDIUM",
      "summary_available": false,
      "detail_available": false,
      "recommended_load": "lazy",
      "max_recommended_size_kb": 500,
      "status": "OK",
      "problem": ""
    },
    {
      "key": "intelligence.contactCoverageSummary",
      "path": "dashboard/api/intelligence/contact-coverage-summary.json",
      "exists": true,
      "first_char": "{",
      "root_type": "object",
      "parsed_from_disk": true,
      "parse_checked_at": "2026-06-12T08:35:08.970Z",
      "valid_json": true,
      "schema_valid": true,
      "record_count": 100,
      "item_count": 5,
      "size_kb": 6.2,
      "bytes": 6360,
      "source_layer": "core",
      "startup_safe": false,
      "load_strategy": "lazy",
      "duplicated_payload_risk": "LOW",
      "summary_available": true,
      "detail_available": true,
      "recommended_load": "summary",
      "max_recommended_size_kb": 100,
      "status": "OK",
      "problem": ""
    },
    {
      "key": "intelligence.contactCoverage",
      "path": "dashboard/api/intelligence/contact-coverage.json",
      "exists": true,
      "first_char": "{",
      "root_type": "object",
      "parsed_from_disk": true,
      "parse_checked_at": "2026-06-12T08:35:08.970Z",
      "valid_json": true,
      "schema_valid": true,
      "record_count": 100,
      "item_count": 100,
      "size_kb": 707.3,
      "bytes": 724305,
      "source_layer": "core",
      "startup_safe": false,
      "load_strategy": "lazy",
      "duplicated_payload_risk": "HIGH",
      "summary_available": true,
      "detail_available": true,
      "recommended_load": "lazy_detail",
      "max_recommended_size_kb": 500,
      "status": "TOO_LARGE",
      "problem": "707KB; summary/detail split recommended"
    },
    {
      "key": "intelligence.complianceExposure",
      "path": "dashboard/api/intelligence/compliance-exposure.json",
      "exists": true,
      "first_char": "{",
      "root_type": "object",
      "parsed_from_disk": true,
      "parse_checked_at": "2026-06-12T08:35:08.970Z",
      "valid_json": true,
      "schema_valid": true,
      "record_count": 7,
      "item_count": 7,
      "size_kb": 61.4,
      "bytes": 62880,
      "source_layer": "core",
      "startup_safe": false,
      "load_strategy": "lazy",
      "duplicated_payload_risk": "LOW",
      "summary_available": false,
      "detail_available": false,
      "recommended_load": "lazy",
      "max_recommended_size_kb": 500,
      "status": "OK",
      "problem": ""
    },
    {
      "key": "intelligence.cleaningWindow",
      "path": "dashboard/api/intelligence/cleaning-window.json",
      "exists": true,
      "first_char": "{",
      "root_type": "object",
      "parsed_from_disk": true,
      "parse_checked_at": "2026-06-12T08:35:08.970Z",
      "valid_json": true,
      "schema_valid": true,
      "record_count": 10,
      "item_count": 10,
      "size_kb": 80.1,
      "bytes": 82006,
      "source_layer": "core",
      "startup_safe": false,
      "load_strategy": "lazy",
      "duplicated_payload_risk": "LOW",
      "summary_available": false,
      "detail_available": false,
      "recommended_load": "lazy",
      "max_recommended_size_kb": 500,
      "status": "OK",
      "problem": ""
    }
  ]
}
